Workbook

Sheet IMPRESSÃO
A1: FORMATO IMPRESSÃO | B1: COR | C1: PREÇO POR IMPRESSÃO
A2: A4 | B2: K | C2: 0.05
A3: SRA4 | B3: K | C3: 0.05
A4: A3 | B4: K | C4: 0.05
A5: SRA3 | B5: K | C5: 0.05
A6: 33x48 | B6: K | C6: 0.05
A7: BANNER | B7: K | C7: 0.12
A8: A4 | B8: CMYK | C8: 0.05
A9: SRA4 | B9: CMYK | C9: 0.05
A10: A3 | B10: CMYK | C10: 0.05
A11: SRA3 | B11: CMYK | C11: 0.05
A12: 33x48 | B12: CMYK | C12: 0.05
A13: BANNER | B13: CMYK | C13: 0.12

Sheet PAPEL
A1: 1 | B1: MARCA | C1: GLOSS / SILK | D1: GRAMAGEM PAPEL | E1: QUANTIDADE | F1: PREÇO | G1: PREÇO / FOLHA
A2: INAPA | D2: 100 | E2: 0 | F2: 0 | G2: =SUM(F2/E2) -> #DIV/0!
A3: INAPA | D3: 125 | E3: 0 | F3: 0 | G3: =SUM(F3/E3) -> #DIV/0!
A4: INAPA | B4: CONDAT | C4: GLOSS | D4: 150 | E4: 20000 | F4: 1212.4 | G4: =SUM(F4/E4) -> 0.06062
A5: INAPA | B5: CONDAT | C5: GLOSS | D5: 170 | E5: 500 | F5: 36.33 | G5: =SUM(F5/E5) -> 0.07266
A6: INAPA | D6: 200 | E6: 0 | F6: 0 | G6: =SUM(F6/E6) -> #DIV/0!
A7: INAPA | B7: CONDAT | C7: GLOSS | D7: 250 | E7: 1000 | F7: 94.58 | G7: =SUM(F7/E7) -> 0.09458
A8: INAPA | B8: CONDAT | C8: SILK | D8: 300 | E8: 500 | F8: 30 | G8: =SUM(F8/E8) -> 0.06
A9: INAPA | B9: CONDAT | C9: SILK | D9: 350 | E9: 1000 | F9: 135.5 | G9: =SUM(F9/E9) -> 0.1355
A10: INAPA | C10: GLOSS | D10: 400 | E10: 125 | F10: 17.91 | G10: =SUM(F10/E10) -> 0.14328
A11: INAPA | D11: IOR 90 Gr. | E11: 500 | F11: 28.55 | G11: =SUM(F11/E11) -> 0.0571
A12: INAPA | B12: MULTIOFT | D12: MULTILOFT ADESIVO 1 FACE BRANCO | E12: 100 | F12: 66.96 | G12: =SUM(F12/E12) -> 0.6696
A13: INAPA | B13: MULTILOFT | D13: MULTILOFT ADESIVO 2 FACES VERDE TURQUESA | E13: 80 | F13: 74.71 | G13: =SUM(F13/E13) -> 0.933875
A14: INAPA | D14: IOR 90 Gr. (64x90 - CORTADO) | E14: 500 | F14: 13.75 | G14: =SUM(F14/E14) -> 0.0275
A15: INAPA | B15: Digilabel Com Cortes | C15: Silk | D15: Autocolante | E15: 1000 | F15: 380 | G15: =SUM(F15/E15) -> 0.38
A16: INAPA | B16: JAC-DATAPOL WHITE GLOSS 32X45 | C16: GLOSS | D16: VINIL AUTOCOLANTE PARA IMP DIGITAL | E16: 100 | F16: 76 | G16: =SUM(F16/E16) -> 0.76
A17: ANTALIS | B17: Polylaser Branco Brilho | C17: GLOSS | D17: VINIL AUTOCOLANTE PARA IMP DIGITAL | E17: 200 | F17: 156.6 | G17: =SUM(F17/E17) -> 0.783
A18: ANTALIS | B18: NOVATECH | C18: DIGITAL SILK | D18: 350Gr | E18: 375 | F18: 58.08 | G18: =SUM(F18/E18) -> 0.15488
A19: ANTALIS | B19: Print Speed Laser Jet,Print Speed, Laserjet, branco, | D19: IOR90 450x640 500un Gr cortado 32x45 -1000un | E19: 1000 | F19: 31.34 | G19: =SUM(F19/E19) -> 0.03134 | H19: =SUM(F19/E19) -> 0.03134
A20: INAPA | E20: 25 | F20: 117.27 | G20: =SUM(F20/E20) -> 4.6908
A21: ANTALIS | B21: Invercote Creato - Invercote, Creato, revestido 2 faces, white, 100% celulose, GZ, 350g/m2, | D21: 350gr | E21: 200 | F21: 87.37 | G21: =SUM(F21/E21) -> 0.43685 | H21: =SUM(F21/E21) -> 0.43685

Sheet ACABAMENTO
A1: CUSTO DE CORTE
A2: FORMATO | B2: VALOR | C2: QUANTIDADE | D2: VALOR TOTAL
A3: NORMAL | B3: 0.02 | C3: 0 | D3: =SUM(C3*B3) -> 0
A4: A5 | B4: 0.02 | C4: 0 | D4: =SUM(C4*B4) -> 0
A5: A4 | B5: 0.02 | C5: 0 | D5: =SUM(C5*B5) -> 0
A6: A3 | B6: 0.02 | C6: 0 | D6: =SUM(C6*B6) -> 0
A7: CARTÃO | B7: 0.05 | C7: 0 | D7: =SUM(C7*B7) -> 0
A8: COM DOBRA | B8: 0.07 | C8: 110 | D8: =SUM(C8*B8) -> 7.7
A9: CARTÕES DE VISITA (ATÉ 1000 UNID.) | B9: 15
A11: PLASTIFICAÇÃO | G11: CUSTO PLASTIFICAÇÃO
A12: MEDIDA | B12: QUANTIDADE | C12: VALOR | D12: QUANTIDADE PASSAGENS | E12: VALOR TOTAL | G12: CUSTO ROLO ROLO + PORTES | H12: QUANT. ROLO CM | I12: CUSTO POR CM | J12: PLANO CM | K12: QUANT. TOTAL PLANOS * | L12: PLASTIF. NECESSÁRIA | M12: CUSTO UNIT. PLANO | N12: VALOR TOTAL
A13: FACE | B13: < 100 | C13: 0.5 | D13: 1 | E13: =SUM(D13*C13) -> 0.5 | G13: 103 | H13: 30000 | I13: =G13/H13 -> 0.0034333333 | J13: 46 | K13: 42 | L13: =J13*K13 -> 1932 | M13: =N13/K13 -> 0.15793333 | N13: =I13*L13 -> 6.6332
B14: < 500 | C14: 0.34 | D14: 1 | E14: =SUM(D14*C14) -> 0.34 | K14: * F/V DUPLICAR QUANT. PLANOS
B15: > 500 | C15: 0.17 | D15: 1 | E15: =SUM(D15*C15) -> 0.17
A16: CARTÕES DE VISITA 1 FACE | C16: 0.16 | D16: 1 | E16: =SUM(C16*D16) -> 0.16
A17: CARTÕES DE VISITA 2 FACES | C17: 0.32 | D17: 1 | E17: =SUM(C17*D17) -> 0.32
A19: LAMINAÇÃO DOURADA | PRATEADA
A20: MEDIDA | B20: QUANTIDADE | C20: VALOR | D20: QUANTIDADE PASSAGENS | E20: VALOR TOTAL
A21: FACE | B21: < 100 | C21: 1.25 | D21: 0 | E21: =SUM(C21*D21) -> 0
B22: < 500 | C22: 0.85 | D22: 1 | E22: =SUM(C22*D22) -> 0.85
B23: > 500 | C23: 0.5 | D23: 0 | E23: =SUM(C23*D23) -> 0
A24: CARTÕES DE VISITA 1 FACE | C24: 0.85 | D24: 0 | E24: =SUM(C24*D24) -> 0
A25: CARTÕES DE VISITA 2 FACES | C25: 1.7 | D25: 0 | E25: =SUM(C25*D25) -> 0
A27: DOBRA QUADRADA
A28: MEDIDA | B28: QUANTIDADE | C28: VALOR | D28: QUANTIDADE PASSAGENS | E28: VALOR TOTAL
A29: A4 | B29: < 100 | C29: 0.5 | D29: 0 | E29: =SUM(C29*D29) -> 0
B30: < 500 | C30: 0.35 | D30: 0 | E30: =SUM(C30*D30) -> 0
B31: > 500 | C31: 0.15 | D31: 0 | E31: =SUM(C31*D31) -> 0
A33: COLA NA LOMBADA
A34: MEDIDA | B34: QUANTIDADE | C34: VALOR | D34: QUANTIDADE PASSAGENS | E34: VALOR TOTAL
A35: A4 | B35: < 100 | C35: 0.5 | D35: 100 | E35: =SUM(C35*D35) -> 50
B36: < 500 | C36: 0.35 | D36: 0 | E36: =SUM(C36*D36) -> 0
B37: > 500 | C37: 0.15 | D37: 0 | E37: =SUM(C37*D37) -> 0
A39: CUSTO DE AGRAFO
B40: QUANTIDADE | C40: VALOR | D40: VALOR TOTAL
B41: 2000 | C41: 20.46 | D41: =C41/B41 -> 0.01023

Sheet CARTÕES DE VISITA
A1: QUANTIDADE ATÉ (X) Unid. | E1: CORTE | G1: PLASTIFICAÇÃO | L1: FOIL | N1: 300m
A2: QUANTIDADE ATÉ (X) Unid. | B2: VALOR | E2: CORTE | F2: CUSTO | G2: CORTE | H2: CUSTO UNIT. PLANO | I2: QUANTIDADE PLANOS | J2: CUSTO | L2: CORTE | M2: CUSTO UNITÁRIO | N2: QUANTIDADE | O2: CUSTO
A3: 50 | B3: 15.2 | E3: ATÉ 1000 UNID. | F3: =SUM(ACABAMENTO!B9) -> 15 | G3: 1 FACE | H3: 0.5 | I3: 0 | J3: =SUM(H3*I3) -> 0 | L3: 1 FACE | M3: =SUM(ACABAMENTO!C24) -> 0.85 | N3: 0 | O3: =SUM(M3*N3) -> 0
A4: 100 | B4: 21.5 | G4: 2 FACES | H4: 1 | I4: 24 | J4: =SUM(H4*I4) -> 24 | L4: 2 FACES | M4: =SUM(ACABAMENTO!C25) -> 1.7 | N4: 12 | O4: =SUM(M4*N4) -> 20.4
A5: 200 | B5: 39.7 | H5: A TRANSPORTAR | J5: =SUM(J3:J4) -> 24 | O5: =SUM(O3:O4) -> 20.4
A6: 300 | B6: 50 | L6: CUSTO PAPEL MULTILOFT
A7: 400 | B7: 66.2 | E7: QUANTIDADE CARTÕES POR PLANO | M7: QUANT. PLANOS | N7: VALOR UNIT. | O7: CUSTO | Q7: PAPEL MULTILOFT | R7: TOTAL PRODUÇÃO | S7: UNIT.
A8: 500 | B8: 77.35 | E8: 21 | L8: PAPEL EXT. | M8: 12 | N8: =SUM(PAPEL!G12) -> 0.6696 | O8: =SUM((M8*2)*N8) -> 16.0704
A9: 1000 | B9: 128.2 | L9: PAPEL INT. | M9: 12 | N9: =SUM(PAPEL!G13) -> 0.933875 | O9: =SUM(M9*N9) -> 11.2065 | Q9: =SUM(O8+O9) -> 27.2769 | R9: =SUM(J20+Q9) -> 58.7769 | S9: =SUM(R9/D20) -> 0.587769
A11: CÁLCULO DE PRODUÇÃO DE CARTÕES DE VISITA | G11: CUSTOS DE ACABAMENTO
A12: CLIENTE | B12: DESCRIÇÃO | C12: REF. | D12: QUANT. | E12: CUSTO IMPRESSÃO | F12: QUANT. FOLHAS | G12: CORTE | H12: PLAST. | I12: FOIL | J12: CUSTO TOTAL | K12: TOTAL UNITÁRIO
A13: SIMPLES | B13: FORMATO 85X55mm IMPRESSÃO 4/4; | D13: 50 | E13: 15.2 | F13: =SUM(D13/E8) -> 2.3809524 | G13: 5 | H13: 0 | I13: 0 | J13: =SUM(E13+G13+H13+I13) -> 20.2 | K13: =SUM(J13/D13) -> 0.404
A14: SIMPLES | B14: FORMATO 85X55mm IMPRESSÃO 4/4; | D14: 100 | E14: 21.5 | F14: =SUM(D14/E8) -> 4.7619048 | G14: 5 | H14: 0 | I14: 0 | J14: =SUM(E14+G14+H14+I14) -> 26.5 | K14: =SUM(J14/D14) -> 0.265
A15: SIMPLES | B15: FORMATO 85X55mm IMPRESSÃO 4/4; | D15: 250 | E15: 44.85 | F15: =SUM(D15/E8) -> 11.904762 | G15: 5 | H15: 0 | I15: 0 | J15: =SUM(E15+G15+H15+I15) -> 49.85 | K15: =SUM(J15/D15) -> 0.1994
A16: SIMPLES | B16: FORMATO 85X55mm IMPRESSÃO 4/4; | D16: 500 | E16: 77.35 | F16: =SUM(D16/E8) -> 23.809524 | G16: 15 | H16: 0 | I16: 0 | J16: =SUM(E16+G16+H16+I16) -> 92.35 | K16: =SUM(J16/D16) -> 0.1847
A17: SIMPLES | B17: FORMATO 85X55mm IMPRESSÃO 4/4; | D17: 750 | E17: 102.78 | F17: =SUM(D17/E8) -> 35.714286 | G17: 15 | H17: 0 | I17: 0 | J17: =SUM(E17+G17+H17+I17) -> 117.78 | K17: =SUM(J17/D17) -> 0.15704
A18: SIMPLES | B18: FORMATO 85X55mm IMPRESSÃO 4/4; | D18: 1000 | E18: 128.2 | F18: =SUM(D18/E8) -> 47.619048 | G18: 15 | H18: 0 | I18: 0 | J18: =SUM(E18+G18+H18+I18) -> 143.2 | K18: =SUM(J18/D18) -> 0.1432
A20: PLASTIFICAÇÃO | B20: FORMATO 85X55mm IMPRESSÃO 4/4; PLASTIFICADO F/V | D20: 100 | E20: 21.5 | F20: =SUM(D20/E8) -> 4.7619048 | G20: 5 | H20: 5 | I20: 0 | J20: =SUM(E20+G20+H20+I20) -> 31.5 | K20: =SUM(J20/D20) -> 0.315
A21: PLASTIFICAÇÃO | B21: FORMATO 85X55mm IMPRESSÃO 4/4; PLASTIFICADO F/V | D21: 250 | E21: 44.85 | F21: =SUM(D21/E8) -> 11.904762 | G21: 5 | H21: 12 | I21: 0 | J21: =SUM(E21+G21+H21+I21) -> 61.85 | K21: =SUM(J21/D21) -> 0.2474
A22: PLASTIFICAÇÃO | B22: FORMATO 85X55mm IMPRESSÃO 4/4; PLASTIFICADO F/V | D22: 500 | E22: 77.35 | F22: =SUM(D22/E8) -> 23.809524 | G22: 15 | H22: 24 | I22: 0 | J22: =SUM(E22+G22+H22+I22) -> 116.35 | K22: =SUM(J22/D22) -> 0.2327
A23: PLASTIFICAÇÃO | B23: FORMATO 85X55mm IMPRESSÃO 4/4; PLASTIFICADO F/V | D23: 750 | E23: 102.78 | F23: =SUM(D23/E8) -> 35.714286 | G23: 15 | H23: 36 | I23: 0 | J23: =SUM(E23+G23+H23+I23) -> 153.78 | K23: =SUM(J23/D23) -> 0.20504
A24: PLASTIFICAÇÃO | B24: FORMATO 85X55mm IMPRESSÃO 4/4; PLASTIFICADO F/V | D24: 1000 | E24: 128.2 | F24: =SUM(D24/E8) -> 47.619048 | G24: 15 | H24: 48 | I24: 0 | J24: =SUM(E24+G24+H24+I24) -> 191.2 | K24: =SUM(J24/D24) -> 0.1912
A26: PLASTIFICAÇÃO + FOIL 1 FACE | B26: FORMATO 85X55mm IMPRESSÃO 4/4; PLASTIFICADO F/V; FOIL FRENTE | D26: 100 | E26: 21.5 | F26: =SUM(D26/E8) -> 4.7619048 | G26: 5 | H26: 5 | I26: 4.25 | J26: =SUM(E26+G26+H26+I26) -> 35.75 | K26: =SUM(J26/D26) -> 0.3575
A27: PLASTIFICAÇÃO + FOIL 1 FACE | B27: FORMATO 85X55mm IMPRESSÃO 4/4; PLASTIFICADO F/V; FOIL 1 FACE | D27: 200 | E27: 44.85 | F27: =SUM(D27/E8) -> 9.5238095 | G27: 5 | H27: 12 | I27: 10.2 | J27: =SUM(E27+G27+H27+I27) -> 72.05 | K27: =SUM(J27/D27) -> 0.36025
A28: PLASTIFICAÇÃO + FOIL 1 FACE | B28: FORMATO 85X55mm IMPRESSÃO 4/4; PLASTIFICADO F/V; FOIL 1 FACE | D28: 500 | E28: 77.35 | F28: =SUM(D28/E8) -> 23.809524 | G28: 15 | H28: 24 | I28: 20.4 | J28: =SUM(E28+G28+H28+I28) -> 136.75 | K28: =SUM(J28/D28) -> 0.2735
A29: PLASTIFICAÇÃO + FOIL 1 FACE | B29: FORMATO 85X55mm IMPRESSÃO 4/4; PLASTIFICADO F/V; FOIL 1 FACE | D29: 750 | E29: 102.78 | F29: =SUM(D29/E8) -> 35.714286 | G29: 15 | H29: 36 | I29: 30.6 | J29: =SUM(E29+G29+H29+I29) -> 184.38 | K29: =SUM(J29/D29) -> 0.24584
A30: PLASTIFICAÇÃO + FOIL 1 FACE | B30: FORMATO 85X55mm IMPRESSÃO 4/4; PLASTIFICADO F/V; FOIL 1 FACE | D30: 1000 | E30: 128.2 | F30: =SUM(D30/E8) -> 47.619048 | G30: 15 | H30: 48 | I30: 40.8 | J30: =SUM(E30+G30+H30+I30) -> 232 | K30: =SUM(J30/D30) -> 0.232
A32: PLASTIFICAÇÃO + FOIL 2 FACES | B32: FORMATO 85X55mm IMPRESSÃO 4/4; PLASTIFICADO F/V; FOIL 2 FACES | D32: 100 | E32: 21.5 | F32: =SUM(D32/E14) -> 4.6511628 | G32: 5 | H32: 5 | I32: 8.5 | J32: =SUM(E32+G32+H32+I32) -> 40 | K32: =SUM(J32/D32) -> 0.4
A33: PLASTIFICAÇÃO + FOIL 2 FACES | B33: FORMATO 85X55mm IMPRESSÃO 4/4; PLASTIFICADO F/V; FOIL 2 FACES | D33: 250 | E33: 44.85 | F33: =SUM(D33/E14) -> 11.627907 | G33: 5 | H33: 12 | I33: 20.4 | J33: =SUM(E33+G33+H33+I33) -> 82.25 | K33: =SUM(J33/D33) -> 0.329
A34: PLASTIFICAÇÃO + FOIL 2 FACES | B34: FORMATO 85X55mm IMPRESSÃO 4/4; PLASTIFICADO F/V; FOIL 2 FACES | D34: 500 | E34: 77.35 | F34: =SUM(D34/E14) -> 23.255814 | G34: 15 | H34: 24 | I34: 0 | J34: =SUM(E34+G34+H34+I34) -> 116.35 | K34: =SUM(J34/D34) -> 0.2327
A35: PLASTIFICAÇÃO + FOIL 2 FACES | B35: FORMATO 85X55mm IMPRESSÃO 4/4; PLASTIFICADO F/V; FOIL 2 FACES | D35: 750 | E35: 102.78 | F35: =SUM(D35/E14) -> 34.883721 | G35: 15 | H35: 36 | I35: 59.5 | J35: =SUM(E35+G35+H35+I35) -> 213.28 | K35: =SUM(J35/D35) -> 0.28437333
A36: PLASTIFICAÇÃO + FOIL 2 FACES | B36: FORMATO 85X55mm IMPRESSÃO 4/4; PLASTIFICADO F/V; FOIL 2 FACES | D36: 1000 | E36: 128.2 | F36: =SUM(D36/E14) -> 46.511628 | G36: 15 | H36: 48 | I36: 79.9 | J36: =SUM(E36+G36+H36+I36) -> 271.1 | K36: =SUM(J36/D36) -> 0.2711
A38: PLASTIFICAÇÃO + FOIL 1 FACE SILACO | B38: FORMATO 85X55mm IMPRESSÃO 4/4; PLASTIFICADO F/V; FOIL 1 FACE | D38: 200 | E38: 44.85 | F38: =SUM(D38/E8) -> 9.5238095 | G38: 5 | H38: 10 | I38: 20.4 | J38: =SUM(E38+G38+H38+I38) -> 80.25 | K38: =SUM(J38/D38) -> 0.40125

Sheet IMPRESSÕES SINGULARES
K1: PLASTIFICAÇÃO | P1: VINCO
A2: FORMATO DE IMPRESSÃO | B2: CUSTO DE IMPRESSÃO | D2: FORMATO | E2: GRAMAGEM | F2: CUSTO UNITÁRIO | H2: CORTE | I2: CUSTO UNITÁRIO | K2: CORTE | L2: CUSTO UNIT. PLANO | M2: QUANTIDADE PLANOS | N2: CUSTO | P2: CORTE | Q2: CUSTO UNITÁRIO
A3: SRA3 CMYK FRENTE | B3: 0.09 | D3: 32x46 | E3: 150 | F3: =SUM(PAPEL!G4) -> 0.06062 | K3: 1 FACE | L3: 0.16 | M3: 0 | N3: =SUM(L3*M3) -> 0 | P3: NORMAL | Q3: =SUM(ACABAMENTO!K3) -> 0
A4: SRA3 CMYK FRENTE / VERSO | B4: 0.16 | E4: 170 | F4: =SUM(PAPEL!G5) -> 0.07266 | H4: COM DOBRA | I4: 0.07 | K4: 2 FACE | L4: 0.32 | M4: 24 | N4: =SUM(L4*M4) -> 7.68 | P4: COM DOBRA | Q4: =SUM(ACABAMENTO!D8) -> 7.7
A5: BANNER CMYK FRENTE | B5: 0.12 | E5: 250 | F5: =SUM(PAPEL!G7) -> 0.09458 | K5: BANNER 1 FACE | L5: 0.32 | M5: 0 | N5: =SUM(L5*M5) -> 0
A6: BANNER CMYK FRENTE / VERSO | B6: 0.24 | E6: 300 | F6: =SUM(PAPEL!G8) -> 0.06 | H6: Total | I6: =E148*I4 -> 70 | K6: BANNER 2 FACE | L6: 0.64 | M6: 0 | N6: =SUM(L6*M6) -> 0
E7: 350 | F7: =SUM(PAPEL!G18) -> 0.15488 | L7: A TRANSPORTAR | N7: =N3+N4+N5+N6 -> 7.68
D8: 32x45 | E8: 90 | F8: 0.04
K9: FOIL | M9: 300m
L10: CUSTO UNITÁRIO | M10: QUANTIDADE | N10: CUSTO
K11: 1 FACE | L11: =SUM(ACABAMENTO!C24) -> 0.85 | M11: 0 | N11: =SUM(L11*M11) -> 0
K12: 2 FACES | L12: =SUM(ACABAMENTO!C25) -> 1.7 | M12: 20 | N12: =SUM(L12*M12) -> 34
N13: =SUM(N11:N12) -> 34
A15: CÁLCULO DE IMPRESSÕES | J15: CUSTOS DE ACABAMENTO
A16: CLIENTE | B16: DESCRIÇÃO | C16: QUANT. | D16: QUANT. POR PLANO | E16: QUANT. PAPEL | F16: CUSTO UNIT. IMP. | G16: CUSTO IMPRESSÃO | H16: CUSTO UNIT. PAPEL | I16: CUSTO PAPEL | J16: CORTE | K16: PLAST. | L16: FOIL | M16: CUSTO TOTAL PROD. | N16: % LUCRO | O16: TOTAL | P16: TOTAL UNIT. | Q16: CUSTO UNI. sem margem
A17: FLYER A6 - FRENTE | C17: 50 | D17: 8 | E17: =SUM(C17/D17) -> 6.25 | F17: 0.09 | G17: =SUM(F17*E17) -> 0.5625 | H17: 0.06 | I17: =SUM(E17*H17) -> 0.375 | J17: 5 | K17: 0 | L17: 0 | M17: =SUM(G17+I17+J17+K17+L17) -> 5.9375 | N17: 3 | O17: =SUM(M17*N17)+M17 -> 23.75
C18: 100 | D18: 8 | E18: =SUM(C18/D18) -> 12.5 | F18: 0.09 | G18: =SUM(F18*E18) -> 1.125 | H18: 0.06 | I18: =SUM(E18*H18) -> 0.75 | J18: 5 | K18: 0 | L18: 0 | M18: =SUM(G18+I18+J18+K18+L18) -> 6.875 | N18: 3 | O18: =SUM(M18*N18)+M18 -> 27.5
C19: 250 | D19: 8 | E19: =SUM(C19/D19) -> 31.25 | F19: 0.09 | G19: =SUM(F19*E19) -> 2.8125 | H19: 0.06 | I19: =SUM(E19*H19) -> 1.875 | J19: 5 | K19: 0 | L19: 0 | M19: =SUM(G19+I19+J19+K19+L19) -> 9.6875 | N19: 3 | O19: =SUM(M19*N19)+M19 -> 38.75
C20: 500 | D20: 8 | E20: =SUM(C20/D20) -> 62.5 | F20: 0.09 | G20: =SUM(F20*E20) -> 5.625 | H20: 0.06 | I20: =SUM(E20*H20) -> 3.75 | J20: 5 | K20: 0 | L20: 0 | M20: =SUM(G20+I20+J20+K20+L20) -> 14.375 | N20: 3 | O20: =SUM(M20*N20)+M20 -> 57.5
C21: 750 | D21: 8 | E21: =SUM(C21/D21) -> 93.75 | F21: 0.09 | G21: =SUM(F21*E21) -> 8.4375 | H21: 0.06 | I21: =SUM(E21*H21) -> 5.625 | J21: 5 | K21: 0 | L21: 0 | M21: =SUM(G21+I21+J21+K21+L21) -> 19.0625 | N21: 3 | O21: =SUM(M21*N21)+M21 -> 76.25
C22: 1000 | D22: 8 | E22: =SUM(C22/D22) -> 125 | F22: 0.09 | G22: =SUM(F22*E22) -> 11.25 | H22: 0.06 | I22: =SUM(E22*H22) -> 7.5 | J22: 15 | K22: 0 | L22: 0 | M22: =SUM(G22+I22+J22+K22+L22) -> 33.75 | N22: 3 | O22: =SUM(M22*N22)+M22 -> 135 | P22: =O22/C22 -> 0.135
A24: FLYER A6 - FRENTE / VERSO | C24: 50 | D24: 8 | E24: =SUM(C24/D24) -> 6.25 | F24: 0.16 | G24: =SUM(F24*E24) -> 1 | H24: 0.06 | I24: =SUM(E24*H24) -> 0.375 | J24: 5 | K24: 0 | L24: 0 | M24: =SUM(G24+I24+J24+K24+L24) -> 6.375 | N24: 3 | O24: =SUM(M24*N24)+M24 -> 25.5
C25: 100 | D25: 8 | E25: =SUM(C25/D25) -> 12.5 | F25: 0.16 | G25: =SUM(F25*E25) -> 2 | H25: 0.06 | I25: =SUM(E25*H25) -> 0.75 | J25: 5 | K25: 7 | L25: 0 | M25: =SUM(G25+I25+J25+K25+L25) -> 14.75 | N25: 3 | O25: =SUM(M25*N25)+M25 -> 59 | P25: =O25/C25 -> 0.59
C26: 250 | D26: 8 | E26: =SUM(C26/D26) -> 31.25 | F26: 0.16 | G26: =SUM(F26*E26) -> 5 | H26: 0.06 | I26: =SUM(E26*H26) -> 1.875 | J26: 5 | K26: 0 | L26: 0 | M26: =SUM(G26+I26+J26+K26+L26) -> 11.875 | N26: 3 | O26: =SUM(M26*N26)+M26 -> 47.5
C27: 500 | D27: 8 | E27: =SUM(C27/D27) -> 62.5 | F27: 0.16 | G27: =SUM(F27*E27) -> 10 | H27: 0.06 | I27: =SUM(E27*H27) -> 3.75 | J27: 15 | K27: 0 | L27: 0 | M27: =SUM(G27+I27+J27+K27+L27) -> 28.75 | N27: 3 | O27: =SUM(M27*N27)+M27 -> 115
C28: 750 | D28: 8 | E28: =SUM(C28/D28) -> 93.75 | F28: 0.16 | G28: =SUM(F28*E28) -> 15 | H28: 0.06 | I28: =SUM(E28*H28) -> 5.625 | J28: 15 | K28: 0 | L28: 0 | M28: =SUM(G28+I28+J28+K28+L28) -> 35.625 | N28: 3 | O28: =SUM(M28*N28)+M28 -> 142.5
C29: 1000 | D29: 8 | E29: =SUM(C29/D29) -> 125 | F29: 0.16 | G29: =SUM(F29*E29) -> 20 | H29: 0.06 | I29: =SUM(E29*H29) -> 7.5 | J29: 15 | K29: 0 | L29: 0 | M29: =SUM(G29+I29+J29+K29+L29) -> 42.5 | N29: 3 | O29: =SUM(M29*N29)+M29 -> 170
A31: FLYER A5 - FRENTE | C31: 50 | D31: 4 | E31: =SUM(C31/D31) -> 12.5 | F31: 0.09 | G31: =SUM(F31*E31) -> 1.125 | H31: 0.06 | I31: =SUM(E31*H31) -> 0.75 | J31: 5 | K31: 0 | L31: 0 | M31: =SUM(G31+I31+J31+K31+L31) -> 6.875 | N31: 3 | O31: =SUM(M31*N31)+M31 -> 27.5
C32: 100 | D32: 4 | E32: =SUM(C32/D32) -> 25 | F32: 0.09 | G32: =SUM(F32*E32) -> 2.25 | H32: 0.06 | I32: =SUM(E32*H32) -> 1.5 | J32: 5 | K32: 0 | L32: 0 | M32: =SUM(G32+I32+J32+K32+L32) -> 8.75 | N32: 3 | O32: =SUM(M32*N32)+M32 -> 35
C33: 200 | D33: 4 | E33: =SUM(C33/D33) -> 50 | F33: 0.05 | G33: =SUM(F33*E33) -> 2.5 | H33: 0.06 | I33: =SUM(E33*H33) -> 3 | J33: 5 | K33: 0 | L33: 0 | M33: =SUM(G33+I33+J33+K33+L33) -> 10.5 | N33: 3 | O33: =SUM(M33*N33)+M33 -> 42
C34: 500 | D34: 4 | E34: =SUM(C34/D34) -> 125 | F34: 0.09 | G34: =SUM(F34*E34) -> 11.25 | H34: 0.06 | I34: =SUM(E34*H34) -> 7.5 | J34: 15 | K34: 0 | L34: 0 | M34: =SUM(G34+I34+J34+K34+L34) -> 33.75 | N34: 3 | O34: =SUM(M34*N34)+M34 -> 135
C35: 750 | D35: 4 | E35: =SUM(C35/D35) -> 187.5 | F35: 0.09 | G35: =SUM(F35*E35) -> 16.875 | H35: 0.06 | I35: =SUM(E35*H35) -> 11.25 | J35: 15 | K35: 0 | L35: 0 | M35: =SUM(G35+I35+J35+K35+L35) -> 43.125 | N35: 3 | O35: =SUM(M35*N35)+M35 -> 172.5
C36: 1000 | D36: 4 | E36: =SUM(C36/D36) -> 250 | F36: 0.09 | G36: =SUM(F36*E36) -> 22.5 | H36: 0.06 | I36: =SUM(E36*H36) -> 15 | J36: 15 | K36: 0 | L36: 0 | M36: =SUM(G36+I36+J36+K36+L36) -> 52.5 | N36: 3 | O36: =SUM(M36*N36)+M36 -> 210
A38: FLYER A5 - FRENTE / VERSO | C38: 50 | D38: 4 | E38: =SUM(C38/D38) -> 12.5 | F38: 0.16 | G38: =SUM(F38*E38) -> 2 | H38: 0.06 | I38: =SUM(E38*H38) -> 0.75 | J38: 5 | K38: 0 | L38: 0 | M38: =SUM(G38+I38+J38+K38+L38) -> 7.75 | N38: 3 | O38: =SUM(M38*N38)+M38 -> 31
C39: 100 | D39: 4 | E39: =SUM(C39/D39) -> 25 | F39: 0.16 | G39: =SUM(F39*E39) -> 4 | H39: 0.06 | I39: =SUM(E39*H39) -> 1.5 | J39: 5 | K39: 0 | L39: 0 | M39: =SUM(G39+I39+J39+K39+L39) -> 10.5 | N39: 3 | O39: =SUM(M39*N39)+M39 -> 42
C40: 250 | D40: 4 | E40: =SUM(C40/D40) -> 62.5 | F40: 0.16 | G40: =SUM(F40*E40) -> 10 | H40: 0.06 | I40: =SUM(E40*H40) -> 3.75 | J40: 5 | K40: 0 | L40: 0 | M40: =SUM(G40+I40+J40+K40+L40) -> 18.75 | N40: 3 | O40: =SUM(M40*N40)+M40 -> 75
C41: 500 | D41: 4 | E41: =SUM(C41/D41) -> 125 | F41: 0.16 | G41: =SUM(F41*E41) -> 20 | H41: 0.06 | I41: =SUM(E41*H41) -> 7.5 | J41: 15 | K41: 0 | L41: 0 | M41: =SUM(G41+I41+J41+K41+L41) -> 42.5 | N41: 3 | O41: =SUM(M41*N41)+M41 -> 170
C42: 750 | D42: 4 | E42: =SUM(C42/D42) -> 187.5 | F42: 0.16 | G42: =SUM(F42*E42) -> 30 | H42: 0.06 | I42: =SUM(E42*H42) -> 11.25 | J42: 15 | K42: 0 | L42: 0 | M42: =SUM(G42+I42+J42+K42+L42) -> 56.25 | N42: 3 | O42: =SUM(M42*N42)+M42 -> 225
C43: 1000 | D43: 4 | E43: =SUM(C43/D43) -> 250 | F43: 0.16 | G43: =SUM(F43*E43) -> 40 | H43: 0.06 | I43: =SUM(E43*H43) -> 15 | J43: 15 | K43: 0 | L43: 0 | M43: =SUM(G43+I43+J43+K43+L43) -> 70 | N43: 3 | O43: =SUM(M43*N43)+M43 -> 280
A45: FLYER A4 - FRENTE / VERSO | C45: 50 | D45: 2 | E45: =SUM(C45/D45) -> 25 | F45: 0.16 | G45: =SUM(F45*E45) -> 4 | H45: 0.06 | I45: =SUM(E45*H45) -> 1.5 | J45: 5 | K45: 0 | L45: 0 | M45: =SUM(G45+I45+J45+K45+L45) -> 10.5 | N45: 3 | O45: =SUM(M45*N45)+M45 -> 42
C46: 100 | D46: 2 | E46: =SUM(C46/D46) -> 50 | F46: 0.16 | G46: =SUM(F46*E46) -> 8 | H46: 0.06 | I46: =SUM(E46*H46) -> 3 | J46: 5 | K46: 0 | L46: 0 | M46: =SUM(G46+I46+J46+K46+L46) -> 16 | N46: 3 | O46: =SUM(M46*N46)+M46 -> 64
C47: 250 | D47: 2 | E47: =SUM(C47/D47) -> 125 | F47: 0.16 | G47: =SUM(F47*E47) -> 20 | H47: 0.06 | I47: =SUM(E47*H47) -> 7.5 | J47: 5 | K47: 0 | L47: 0 | M47: =SUM(G47+I47+J47+K47+L47) -> 32.5 | N47: 3 | O47: =SUM(M47*N47)+M47 -> 130
C48: 500 | D48: 2 | E48: =SUM(C48/D48) -> 250 | F48: 0.16 | G48: =SUM(F48*E48) -> 40 | H48: 0.06 | I48: =SUM(E48*H48) -> 15 | J48: 15 | K48: 0 | L48: 0 | M48: =SUM(G48+I48+J48+K48+L48) -> 70 | N48: 3 | O48: =SUM(M48*N48)+M48 -> 280
C49: 750 | D49: 2 | E49: =SUM(C49/D49) -> 375 | F49: 0.16 | G49: =SUM(F49*E49) -> 60 | H49: 0.06 | I49: =SUM(E49*H49) -> 22.5 | J49: 15 | K49: 0 | L49: 0 | M49: =SUM(G49+I49+J49+K49+L49) -> 97.5 | N49: 3 | O49: =SUM(M49*N49)+M49 -> 390
C50: 1000 | D50: 2 | E50: =SUM(C50/D50) -> 500 | F50: 0.16 | G50: =SUM(F50*E50) -> 80 | H50: 0.06 | I50: =SUM(E50*H50) -> 30 | J50: 15 | K50: 0 | L50: 0 | M50: =SUM(G50+I50+J50+K50+L50) -> 125 | N50: 3 | O50: =SUM(M50*N50)+M50 -> 500
A52: CARTAZ A4 - FRENTE | C52: 50 | D52: 2 | E52: =SUM(C52/D52) -> 25 | F52: 0.09 | G52: =SUM(F52*E52) -> 2.25 | H52: 0.06 | I52: =SUM(E52*H52) -> 1.5 | J52: 5 | K52: 0 | L52: 0 | M52: =SUM(G52+I52+J52+K52+L52) -> 8.75 | N52: 3 | O52: =SUM(M52*N52)+M52 -> 35
C53: 100 | D53: 2 | E53: =SUM(C53/D53) -> 50 | F53: 0.09 | G53: =SUM(F53*E53) -> 4.5 | H53: 0.06 | I53: =SUM(E53*H53) -> 3 | J53: 5 | K53: 0 | L53: 0 | M53: =SUM(G53+I53+J53+K53+L53) -> 12.5 | N53: 3 | O53: =SUM(M53*N53)+M53 -> 50
C54: 250 | D54: 2 | E54: =SUM(C54/D54) -> 125 | F54: 0.09 | G54: =SUM(F54*E54) -> 11.25 | H54: 0.06 | I54: =SUM(E54*H54) -> 7.5 | J54: 5 | K54: 0 | L54: 0 | M54: =SUM(G54+I54+J54+K54+L54) -> 23.75 | N54: 3 | O54: =SUM(M54*N54)+M54 -> 95
C55: 500 | D55: 2 | E55: =SUM(C55/D55) -> 250 | F55: 0.09 | G55: =SUM(F55*E55) -> 22.5 | H55: 0.06 | I55: =SUM(E55*H55) -> 15 | J55: 15 | K55: 0 | L55: 0 | M55: =SUM(G55+I55+J55+K55+L55) -> 52.5 | N55: 3 | O55: =SUM(M55*N55)+M55 -> 210
C56: 750 | D56: 2 | E56: =SUM(C56/D56) -> 375 | F56: 0.09 | G56: =SUM(F56*E56) -> 33.75 | H56: 0.06 | I56: =SUM(E56*H56) -> 22.5 | J56: 15 | K56: 0 | L56: 0 | M56: =SUM(G56+I56+J56+K56+L56) -> 71.25 | N56: 3 | O56: =SUM(M56*N56)+M56 -> 285
C57: 1000 | D57: 2 | E57: =SUM(C57/D57) -> 500 | F57: 0.09 | G57: =SUM(F57*E57) -> 45 | H57: 0.06 | I57: =SUM(E57*H57) -> 30 | J57: 15 | K57: 0 | L57: 0 | M57: =SUM(G57+I57+J57+K57+L57) -> 90 | N57: 3 | O57: =SUM(M57*N57)+M57 -> 360
A59: CARTAZ A3 / SRA3 - FRENTE | C59: 50 | D59: 1 | E59: =SUM(C59/D59) -> 50 | F59: 0.09 | G59: =SUM(F59*E59) -> 4.5 | H59: 0.06 | I59: =SUM(E59*H59) -> 3 | J59: 5 | K59: 0 | L59: 0 | M59: =SUM(G59+I59+J59+K59+L59) -> 12.5 | N59: 3 | O59: =SUM(M59*N59)+M59 -> 50
C60: 100 | D60: 1 | E60: =SUM(C60/D60) -> 100 | F60: 0.09 | G60: =SUM(F60*E60) -> 9 | H60: 0.06 | I60: =SUM(E60*H60) -> 6 | J60: 0 | K60: 0 | L60: 0 | M60: =SUM(G60+I60+J60+K60+L60) -> 15 | N60: 3 | O60: =SUM(M60*N60)+M60 -> 60
C61: 250 | D61: 1 | E61: =SUM(C61/D61) -> 250 | F61: 0.09 | G61: =SUM(F61*E61) -> 22.5 | H61: 0.14 | I61: =SUM(E61*H61) -> 35 | J61: 15 | K61: 0 | L61: 0 | M61: =SUM(G61+I61+J61+K61+L61) -> 72.5 | N61: 3 | O61: =SUM(M61*N61)+M61 -> 290 | P61: =O61/C61 -> 1.16
C62: 500 | D62: 1 | E62: =SUM(C62/D62) -> 500 | F62: 0.09 | G62: =SUM(F62*E62) -> 45 | H62: 0.06 | I62: =SUM(E62*H62) -> 30 | J62: 15 | K62: 0 | L62: 0 | M62: =SUM(G62+I62+J62+K62+L62) -> 90 | N62: 3 | O62: =SUM(M62*N62)+M62 -> 360
C63: 750 | D63: 1 | E63: =SUM(C63/D63) -> 750 | F63: 0.09 | G63: =SUM(F63*E63) -> 67.5 | H63: 0.06 | I63: =SUM(E63*H63) -> 45 | J63: 15 | K63: 0 | L63: 0 | M63: =SUM(G63+I63+J63+K63+L63) -> 127.5 | N63: 3 | O63: =SUM(M63*N63)+M63 -> 510
C64: 1000 | D64: 1 | E64: =SUM(C64/D64) -> 1000 | F64: 0.09 | G64: =SUM(F64*E64) -> 90 | H64: 0.06 | I64: =SUM(E64*H64) -> 60 | J64: 15 | K64: 0 | L64: 0 | M64: =SUM(G64+I64+J64+K64+L64) -> 165 | N64: 3 | O64: =SUM(M64*N64)+M64 -> 660
A66: PETFILLING | B66: Voucher 110x215mm | C66: 700 | D66: 4 | E66: =SUM(C66/D66) -> 175 | F66: 0.16 | G66: =SUM(F66*E66) -> 28 | H66: 0.11 | I66: =SUM(E66*H66) -> 19.25 | J66: 15 | K66: 0 | L66: 0 | M66: =SUM(G66+I66+J66+K66+L66) -> 62.25 | N66: 3 | O66: =SUM(M66*N66)+M66 -> 249
A67: WMG | B67: ETIQUETAS FRÁGIL | C67: 600 | D67: 6 | E67: =SUM(C67/D67) -> 100 | F67: 0.09 | G67: =SUM(F67*E67) -> 9 | H67: 0.38 | I67: =SUM(E67*H67) -> 38 | J67: 15 | K67: 0 | L67: 0 | M67: =SUM(G67+I67+J67+K67+L67) -> 62 | N67: 2 | O67: =SUM(M67*N67)+M67 -> 186
B68: 65X110MMM
A69: LOJA SANTO ANTÓNIO | B69: Pagela Oração do Anjo 65x110mm | C69: 300 | D69: 16 | E69: =SUM(C69/D69) -> 18.75 | F69: 0.16 | G69: =SUM(F69*E69) -> 3 | H69: 0.06 | I69: =SUM(E69*H69) -> 1.125 | J69: 5 | K69: 0 | L69: 0 | M69: =SUM(G69+I69+J69+K69+L69) -> 9.125 | N69: 3 | O69: =SUM(M69*N69)+M69 -> 36.5
A70: LOJA SANTO ANTÓNIO | B70: Pagela Terço 75x220mm | C70: 100 | D70: 8 | E70: =SUM(C70/D70) -> 12.5 | F70: 0.16 | G70: =SUM(F70*E70) -> 2 | H70: 0.073 | I70: =SUM(E70*H70) -> 0.9125 | J70: 5 | K70: 0 | L70: 0 | M70: =SUM(G70+I70+J70+K70+L70) -> 7.9125 | N70: 3 | O70: =SUM(M70*N70)+M70 -> 31.65
A71: LOJA SANTO ANTÓNIO | B71: Cartaz Ceia 453x224mm | C71: 30 | D71: 1 | E71: =SUM(C71/D71) -> 30 | F71: 0.09 | G71: =SUM(F71*E71) -> 2.7 | H71: 0.073 | I71: =SUM(E71*H71) -> 2.19 | J71: 5 | K71: 0 | L71: 0 | M71: =SUM(G71+I71+J71+K71+L71) -> 9.89 | N71: 3 | O71: =SUM(M71*N71)+M71 -> 39.56
A72: LOJA SANTO ANTÓNIO | B72: Etiquetas para Caixa Terços | C72: 300 | D72: 15 | E72: =SUM(C72/D72) -> 20 | F72: 0.09 | G72: =SUM(F72*E72) -> 1.8 | H72: 0.38 | I72: =SUM(E72*H72) -> 7.6 | J72: 15 | K72: 0 | L72: 0 | M72: =SUM(G72+I72+J72+K72+L72) -> 24.4 | N72: 3 | O72: =SUM(M72*N72)+M72 -> 97.6
A73: LOJA SANTO ANTÓNIO | B73: Cartão 80x80mm | C73: 200 | D73: 15 | E73: =SUM(C73/D73) -> 13.333333 | F73: 0.09 | G73: =SUM(F73*E73) -> 1.2 | H73: 0.11 | I73: =SUM(E73*H73) -> 1.4666667 | J73: 5 | K73: 0 | L73: 0 | M73: =SUM(G73+I73+J73+K73+L73) -> 7.6666667 | N73: 3 | O73: =SUM(M73*N73)+M73 -> 30.666667
A74: LOJA SANTO ANTÓNIO | B74: Pagela Moldura | C74: 400 | D74: 16 | E74: =SUM(C74/D74) -> 25 | F74: 0.16 | G74: =SUM(F74*E74) -> 4 | H74: 0.073 | I74: =SUM(E74*H74) -> 1.825 | J74: 15 | K74: 0 | L74: 0 | M74: =SUM(G74+I74+J74+K74+L74) -> 20.825 | N74: 3 | O74: =SUM(M74*N74)+M74 -> 83.3
A75: LOJA SANTO ANTÓNIO | B75: Pagela Rosario 87x120 | C75: 100 | D75: 9 | E75: =SUM(C75/D75) -> 11.111111 | F75: 0.16 | G75: =SUM(F75*E75) -> 1.7777778 | H75: 0.073 | I75: =SUM(E75*H75) -> 0.81111111 | J75: 5 | K75: 0 | L75: 0 | M75: =SUM(G75+I75+J75+K75+L75) -> 7.5888889 | N75: 3 | O75: =SUM(M75*N75)+M75 -> 30.355556
A76: LOJA SANTO ANTÓNIO | B76: Cartão 120x120mm | C76: 200 | D76: 6 | E76: =SUM(C76/D76) -> 33.333333 | F76: 0.09 | G76: =SUM(F76*E76) -> 3 | H76: 0.11 | I76: =SUM(E76*H76) -> 3.6666667 | J76: 5 | K76: 0 | L76: 0 | M76: =SUM(G76+I76+J76+K76+L76) -> 11.666667 | N76: 3 | O76: =SUM(M76*N76)+M76 -> 46.666667
C77: 0 | D77: 0 | E77: =SUM(C77/D77) -> #DIV/0! | F77: 0.09 | G77: =SUM(F77*E77) -> #DIV/0! | H77: 0 | I77: =SUM(E77*H77) -> #DIV/0! | J77: 15 | K77: 0 | M77: =SUM(G77+I77+J77+K77+L77) -> #DIV/0! | N77: 3
A78: Verdasca | B78: Diptico A5 | C78: 3000 | D78: 2 | E78: =SUM(C78/D78) -> 1500 | F78: 0.16 | G78: =SUM(F78*E78) -> 240 | H78: 0.11 | I78: =SUM(E78*H78) -> 165 | J78: 15 | K78: 0 | L78: 550 | M78: =SUM(G78+I78+J78+K78+L78) -> 970 | N78: 1.5 | O78: =SUM((M78*N78)+M78) -> 2425 | P78: =O78/C78 -> 0.80833333
O79: =SUM((M79*N79)+M79) -> 0
A80: Mercedes | B80: Convite 21,5x21cm, Aberto | C80: 160 | D80: 2 | E80: =SUM(C80/D80) -> 80 | F80: 0.16 | G80: =SUM(F80*E80) -> 12.8 | H80: 0.06 | I80: =SUM(E80*H80) -> 4.8 | J80: 15 | K80: 25 | L80: 44 | M80: =SUM(G80+I80+J80+K80+L80) -> 101.6 | N80: 3 | O80: =SUM((M80*N80)+M80) -> 406.4 | P80: =O80/C80 -> 2.54
A81: MERCEDES | B81: Cartão a5 210x148 laminado | C81: 850 | D81: 4 | E81: =SUM(C81/D81) -> 212.5 | F81: 0.16 | G81: =SUM(F81*E81) -> 34 | H81: 0.18 | I81: =SUM(E81*H81) -> 38.25 | J81: 35 | K81: 68.16 | L81: 0 | M81: =SUM(G81+I81+J81+K81+L81) -> 175.41 | N81: 3 | O81: =SUM((M81*N81)+M81) -> 701.64 | P81: =O81/C81 -> 0.82545882 | Q81: =M81/C81 -> 0.20636471
A82: MERCEDES | B82: Cartão a5 210x148 simples | C82: 850 | D82: 4 | E82: =SUM(C82/D82) -> 212.5 | F82: 0.16 | G82: =SUM(F82*E82) -> 34 | H82: 0.18 | I82: =SUM(E82*H82) -> 38.25 | J82: 35 | K82: 0 | L82: 0 | M82: =SUM(G82+I82+J82+K82+L82) -> 107.25 | N82: 3 | O82: =SUM((M82*N82)+M82) -> 429 | P82: =O82/C82 -> 0.50470588 | Q82: =M82/C82 -> 0.12617647
A83: MERCEDES | B83: Cartão a4 com dobra a5 laminado | C83: 860 | D83: 2 | E83: =SUM(C83/D83) -> 430 | F83: 0.16 | G83: =SUM(F83*E83) -> 68.8 | H83: 0.15 | I83: =SUM(E83*H83) -> 64.5 | J83: 105 | K83: 137.6 | L83: 0 | M83: =SUM(G83+I83+J83+K83+L83) -> 375.9 | N83: 3 | O83: =SUM((M83*N83)+M83) -> 1503.6 | P83: =O83/C83 -> 1.7483721 | Q83: =M83/C83 -> 0.43709302
A84: MERCEDES | B84: Cartão a4 com dobra a5 | C84: 860 | D84: 2 | E84: =SUM(C84/D84) -> 430 | F84: 0.16 | G84: =SUM(F84*E84) -> 68.8 | H84: 0.15 | I84: =SUM(E84*H84) -> 64.5 | J84: 105 | K84: 0 | L84: 0 | M84: =SUM(G84+I84+J84+K84+L84) -> 238.3 | N84: 3 | O84: =SUM((M84*N84)+M84) -> 953.2 | P84: =O84/C84 -> 1.1083721 | Q84: =M84/C84 -> 0.27709302
A86: CLARA E GEMA | B86: Autocolante camponios | C86: 16 | D86: 2 | E86: =SUM(C86/D86) -> 8 | F86: 0.09 | G86: =SUM(F86*E86) -> 0.72 | H86: 0.38 | I86: =SUM(E86*H86) -> 3.04 | J86: 0 | K86: 0 | L86: 0 | M86: =SUM(G86+I86+J86+K86+L86) -> 3.76 | N86: 3 | O86: =SUM((M86*N86)+M86) -> 15.04
A88: casamentos | B88: Pagelas Casamento | C88: 280 | D88: 8 | E88: =SUM(C88/D88) -> 35 | F88: 0.16 | G88: =SUM(F88*E88) -> 5.6 | H88: 0.38 | I88: =SUM(E88*H88) -> 13.3 | J88: 5 | K88: 0 | L88: 0 | M88: =SUM(G88+I88+J88+K88+L88) -> 23.9 | N88: 3 | O88: =SUM((M88*N88)+M88) -> 95.6
A90: ARTMA | B90: FLYER 95x188 | C90: 500 | D90: 6 | E90: =SUM(C90/D90) -> 83.333333 | F90: 0.16 | G90: =SUM(F90*E90) -> 13.333333 | H90: 0.06 | I90: =SUM(E90*H90) -> 5 | J90: 15 | K90: 0 | L90: 0 | M90: =SUM(G90+I90+J90+K90+L90) -> 33.333333 | N90: 3 | O90: =SUM((M90*N90)+M90) -> 133.33333
B91: FLYER 95x188 | C91: 1000 | D91: 6 | E91: =SUM(C91/D91) -> 166.66667 | F91: 0.16 | G91: =SUM(F91*E91) -> 26.666667 | H91: 0.06 | I91: =SUM(E91*H91) -> 10 | J91: 15 | K91: 0 | L91: 0 | M91: =SUM(G91+I91+J91+K91+L91) -> 51.666667 | N91: 3 | O91: =SUM((M91*N91)+M91) -> 206.66667
C92: 0 | D92: 0 | E92: =SUM(C92/D92) -> #DIV/0! | F92: 0.09 | G92: =SUM(F92*E92) -> #DIV/0! | H92: 0 | I92: =SUM(E92*H92) -> #DIV/0! | J92: 15 | K92: 0 | L92: ACABAMENTO | M92: =SUM(G92+I92+J92+K92+L92) -> #DIV/0! | N92: 3
A93: ABEA | B93: Diptico A5 | C93: 250 | D93: 2 | E93: =SUM(C93/D93) -> 125 | F93: 0.16 | G93: =SUM(F93*E93) -> 20 | H93: 0.06 | I93: =SUM(E93*H93) -> 7.5 | J93: 15 | K93: 0 | L93: 20 | M93: =SUM(G93+I93+J93+K93+L93) -> 62.5 | N93: 2 | O93: =SUM((M93*N93)+M93) -> 187.5 | P93: =O93/C93 -> 0.75
A94: festas bairro | B94: EMENTA BAIRRO | C94: 60 | D94: 1 | E94: =SUM(C94/D94) -> 60 | F94: 0.09 | G94: =SUM(F94*E94) -> 5.4 | H94: 0.15 | I94: =SUM(E94*H94) -> 9 | J94: 15 | K94: 19.2 | L94: 20 | M94: =SUM(G94+I94+J94+K94+L94) -> 68.6 | N94: 2 | O94: =SUM((M94*N94)+M94) -> 205.8 | P94: =O94/C94 -> 3.43
C95: 0 | D95: 0 | E95: =SUM(C95/D95) -> #DIV/0! | F95: 0.09 | G95: =SUM(F95*E95) -> #DIV/0! | H95: 0 | I95: =SUM(E95*H95) -> #DIV/0! | J95: 15 | K95: 0 | L95: 0 | M95: =SUM(G95+I95+J95+K95+L95) -> #DIV/0! | N95: 3
A96: CLARA E GEMA | B96: Folha autocolante impressa | C96: 400 | D96: 8 | E96: =SUM(C96/D96) -> 50 | F96: 0.09 | G96: =SUM(F96*E96) -> 4.5 | H96: 0.38 | I96: =SUM(E96*H96) -> 19 | J96: 5 | K96: 0 | L96: 0 | M96: =SUM(G96+I96+J96+K96+L96) -> 28.5 | N96: 3 | O96: =SUM((M96*N96)+M96) -> 114
C97: 0 | D97: 0 | E97: =SUM(C97/D97) -> #DIV/0! | F97: 0.09 | G97: =SUM(F97*E97) -> #DIV/0! | H97: 0 | I97: =SUM(E97*H97) -> #DIV/0! | J97: 15 | K97: 0 | L97: 0 | M97: =SUM(G97+I97+J97+K97+L97) -> #DIV/0! | N97: 3
A98: AVENAL | B98: PAPEL VINIL 220x90 | C98: 1000 | D98: 6 | E98: =SUM(C98/D98) -> 166.66667 | F98: 0.09 | G98: =SUM(F98*E98) -> 15 | H98: 0.78 | I98: =SUM(E98*H98) -> 130 | J98: 5 | K98: 0 | L98: 0 | M98: =SUM(G98+I98+J98+K98+L98) -> 150 | N98: 0.6 | O98: =SUM((M98*N98)+M98) -> 240 | P98: =O98/C98 -> 0.24
C99: 0 | D99: 0 | E99: =SUM(C99/D99) -> #DIV/0! | F99: 0.09 | G99: =SUM(F99*E99) -> #DIV/0! | H99: 0 | I99: =SUM(E99*H99) -> #DIV/0! | J99: 15 | K99: 0 | L99: 0 | M99: =SUM(G99+I99+J99+K99+L99) -> #DIV/0! | N99: 3
A100: FET | B100: Impressão A5 duatlo | C100: 500 | D100: 4 | E100: =SUM(C100/D100) -> 125 | F100: 0.09 | G100: =SUM(F100*E100) -> 11.25 | H100: 0.06 | I100: =SUM(E100*H100) -> 7.5 | J100: 10 | K100: 0 | L100: 0 | M100: =SUM(G100+I100+J100+K100+L100) -> 28.75 | N100: 0.2 | O100: =SUM((M100*N100)+M100) -> 34.5 | P100: =O100/C100 -> 0.069
A101: FET | B101: Cartaz A3 Constragimento duatlo | C101: 3 | D101: 1 | E101: =SUM(C101/D101) -> 3 | F101: 0.09 | G101: =SUM(F101*E101) -> 0.27 | H101: 0.06 | I101: =SUM(E101*H101) -> 0.18 | J101: 15 | K101: 0 | L101: 0 | M101: =SUM(G101+I101+J101+K101+L101) -> 15.45 | N101: 0.2 | O101: =SUM((M101*N101)+M101) -> 18.54 | P101: =O101/C101 -> 6.18 | Q101: TOTAL
A102: FET | B102: Cartaz A5 F/V Constragimento duatlo | C102: 40 | D102: 2 | E102: =SUM(C102/D102) -> 20 | F102: 0.16 | G102: =SUM(F102*E102) -> 3.2 | H102: 0.06 | I102: =SUM(E102*H102) -> 1.2 | J102: 15 | K102: 0 | L102: 0 | M102: =SUM(G102+I102+J102+K102+L102) -> 19.4 | N102: 0.2 | O102: =SUM((M102*N102)+M102) -> 23.28 | P102: =O102/C102 -> 0.582 | Q102: =SUM(O100:O105) -> 174.27
A103: FET | B103: Impressão A5 reis | C103: 500 | D103: 4 | E103: =SUM(C103/D103) -> 125 | F103: 0.09 | G103: =SUM(F103*E103) -> 11.25 | H103: 0.06 | I103: =SUM(E103*H103) -> 7.5 | J103: 10 | K103: 0 | L103: 0 | M103: =SUM(G103+I103+J103+K103+L103) -> 28.75 | N103: 0.2 | O103: =SUM((M103*N103)+M103) -> 34.5 | P103: =O103/C103 -> 0.069
A104: FET | B104: Cartaz A3 reis | C104: 15 | D104: 1 | E104: =SUM(C104/D104) -> 15 | F104: 0.09 | G104: =SUM(F104*E104) -> 1.35 | H104: 0.06 | I104: =SUM(E104*H104) -> 0.9 | J104: 15 | K104: 0 | L104: 0 | M104: =SUM(G104+I104+J104+K104+L104) -> 17.25 | N104: 0.2 | O104: =SUM((M104*N104)+M104) -> 20.7 | P104: =O104/C104 -> 1.38
A105: FET | B105: Cartaz A6 reis | C105: 1100 | D105: 8 | E105: =SUM(C105/D105) -> 137.5 | F105: 0.09 | G105: =SUM(F105*E105) -> 12.375 | H105: 0.06 | I105: =SUM(E105*H105) -> 8.25 | J105: 15 | K105: 0 | L105: 0 | M105: =SUM(G105+I105+J105+K105+L105) -> 35.625 | N105: 0.2 | O105: =SUM((M105*N105)+M105) -> 42.75 | P105: =O105/C105 -> 0.038863636
C106: 0 | D106: 0 | E106: =SUM(C106/D106) -> #DIV/0! | F106: 0.09 | G106: =SUM(F106*E106) -> #DIV/0! | H106: 0 | I106: =SUM(E106*H106) -> #DIV/0! | J106: 15 | K106: 0 | L106: 0 | M106: =SUM(G106+I106+J106+K106+L106) -> #DIV/0! | N106: 3
A107: urna acrilico | B107: PAPEL VINIL 220x90 | C107: 1 | D107: 1 | E107: =SUM(C107/D107) -> 1 | F107: 0.09 | G107: =SUM(F107*E107) -> 0.09 | H107: 0.78 | I107: =SUM(E107*H107) -> 0.78 | J107: 0 | K107: 0 | L107: 0 | M107: =SUM(G107+I107+J107+K107+L107) -> 0.87 | N107: 3 | O107: =SUM((M107*N107)+M107) -> 3.48 | P107: =O107/C107 -> 3.48
C108: 0 | D108: 0 | E108: =SUM(C108/D108) -> #DIV/0! | F108: 0.09 | G108: =SUM(F108*E108) -> #DIV/0! | H108: 0 | I108: =SUM(E108*H108) -> #DIV/0! | J108: 15 | K108: 0 | L108: 0 | M108: =SUM(G108+I108+J108+K108+L108) -> #DIV/0! | N108: 3
A109: digiwest | B109: folha timbrada » | C109: 500 | D109: 2 | E109: =SUM(C109/D109) -> 250 | F109: 0.09 | G109: =SUM(F109*E109) -> 22.5 | H109: 0.78 | I109: =SUM(E109*H109) -> 195 | J109: 0 | K109: 0 | L109: 0 | M109: =SUM(G109+I109+J109+K109+L109) -> 217.5 | N109: 3 | O109: =SUM((M109*N109)+M109) -> 870 | P109: =O109/C109 -> 1.74
A110: Pianos | B110: folha timbrada » | C110: 500 | D110: 2 | E110: =SUM(C110/D110) -> 250 | F110: 0.09 | G110: =SUM(F110*E110) -> 22.5 | H110: 0.03 | I110: =SUM(E110*H110) -> 7.5 | J110: 10 | K110: 0 | L110: 0 | M110: =SUM(G110+I110+J110+K110+L110) -> 40 | N110: 2 | O110: =SUM((M110*N110)+M110) -> 120 | P110: =O110/C110 -> 0.24
A111: Pianos | B111: cartões | C111: 250 | D111: 12 | E111: =SUM(C111/D111) -> 20.833333 | F111: 0.16 | G111: =SUM(F111*E111) -> 3.3333333 | H111: 0.15 | I111: =SUM(E111*H111) -> 3.125 | J111: 5 | K111: 4 | L111: 0 | M111: =SUM(G111+I111+J111+K111+L111) -> 15.458333 | N111: 3 | O111: =SUM((M111*N111)+M111) -> 61.833333 | P111: =O111/C111 -> 0.24733333 | Q111: =M111/C111 -> 0.061833333
...

Sheet CÁLCULO CATALOGOS
D1: PAPEL | H1: CORTE | K1: PLASTIFICAÇÃO (VALOR COM MARGEM DE LUCRO) | Q1: LAMINAÇÃO FOIL (VALOR COM MARGEM LUCRO)
A2: FORMATO DE IMPRESSÃO | B2: CUSTO DE IMPRESSÃO | D2: FORMATO | E2: GRAMAGEM | F2: CUSTO UNITÁRIO | H2: CORTE | I2: CUSTO UNITÁRIO | L2: CUSTO UNITÁRIO | M2: QUANT. | N2: CUSTO TOTAL | R2: CUSTO UNITÁRIO | S2: QUANT. | T2: CUSTO TOTAL
A3: SRA3 CMYK | B3: =SUM('IMPRESSÃO'!C5) -> 0.05 | D3: SRA3 | E3: 150 | F3: =SUM(PAPEL!G4) -> 0.06062 | H3: NORMAL | I3: =SUM(ACABAMENTO!B3) -> 0.02 | K3: < 100 | L3: =SUM(ACABAMENTO!C13) -> 0.5 | M3: 0 | N3: =SUM(L3*M3) -> 0 | Q3: < 100 | R3: =SUM(ACABAMENTO!C21) -> 1.25 | S3: 0 | T3: =SUM(R3*S3) -> 0
A4: banner | B4: 0.12 | E4: 170 | F4: =SUM(PAPEL!G5) -> 0.07266 | H4: COM DOBRA | I4: =SUM(ACABAMENTO!B8) -> 0.07 | K4: < 500 | L4: =SUM(ACABAMENTO!C14) -> 0.34 | M4: 0 | N4: =SUM(L4*M4) -> 0 | Q4: < 500 | R4: =SUM(ACABAMENTO!C22) -> 0.85 | S4: 0 | T4: =SUM(R4*S4) -> 0
E5: 250 | F5: =SUM(PAPEL!G7) -> 0.09458 | G5: A TRANSPORTAR | K5: > 500 | L5: =SUM(ACABAMENTO!C15) -> 0.17 | M5: 500 | N5: =SUM(L5*M5) -> 85 | Q5: > 500 | R5: =SUM(ACABAMENTO!C23) -> 0.5 | S5: 1000 | T5: =SUM(R5*S5) -> 500
E6: 300 | F6: =SUM(PAPEL!G8) -> 0.06 | L6: A TRANSPORTAR | N6: =SUM(N3:N5) -> 85 | R6: A TRANSPORTAR | T6: =SUM(T3:T5) -> 500
A7: DOBRA - VALOR COM MARGEM DE LUCRO | F7: COLA (VALOR COM MARGEM DE LUCRO) | K7: INSERIR QUANTIDADE A CALCULAR
B8: CUSTO UNITÁRIO | C8: QUANT. | D8: CUSTO TOTAL | G8: CUSTO UNITÁRIO | H8: QUANT. | I8: CUSTO TOTAL | K8: < 100 | L8: 0 | P8: CUSTO DE AGRAFO
A9: < 100 | B9: =SUM(ACABAMENTO!C29) -> 0.5 | C9: 100 | D9: =SUM(B9*C9) -> 50 | F9: < 100 | G9: =SUM(ACABAMENTO!C35) -> 0.5 | H9: 0 | I9: =SUM(G9*H9) -> 0 | K9: < 500 | L9: 0 | P9: Unidade | Q9: =ACABAMENTO!D41 -> 0.01023
A10: < 500 | B10: =SUM(ACABAMENTO!C30) -> 0.35 | C10: 0 | D10: =SUM(B10*C10) -> 0 | F10: < 500 | G10: =SUM(ACABAMENTO!C36) -> 0.35 | H10: 0 | I10: =SUM(G10*H10) -> 0 | K10: > 500 | L10: 500 | P10: Quantidade Total | Q10: 2000
A11: > 500 | B11: =SUM(ACABAMENTO!C31) -> 0.15 | C11: 0 | D11: =SUM(B11*C11) -> 0 | F11: > 500 | G11: =SUM(ACABAMENTO!C37) -> 0.15 | H11: 1000 | I11: =SUM(G11*H11) -> 150 | P11: CUSTO TOTAL | Q11: =Q9*Q10 -> 20.46
B12: A TRANSPORTAR | D12: =SUM(D9:D11) -> 50 | G12: A TRANSPORTAR | I12: =SUM(I9:I11) -> 150
A13: DESCRIÇÃO CATÁLOGOS | J13: CUSTOS DE ACABAMENTO | O13: CÁLCULO DE PRODUÇÃO DE CATÁLOGOS
A14: CLIENTE | B14: DESCRIÇÃO | C14: QUANT. | D14: QUANT. PÁGINAS | E14: FACES IMPRESSAS | F14: CUSTO IMPRESSÃO | G14: QUANT. FOLHAS | H14: CUSTO UNIT. PAPEL | I14: CUSTO PAPEL | J14: CORTE (22€/HORA) | K14: PLAST. | L14: FOIL | M14: AGRAFO DOBRA | N14: COLA | O14: CUSTO TOTAL PROD. | P14: CUSTO UNIT. PROD. | Q14: % LUCRO | R14: TOTAL | S14: TOTAL UNITÁRIO
A15: VERDASCA | B15: CAPA BROCHURA PAV. PAPEL 250 GRS | C15: 500 | D15: 4 | E15: =SUM(((C15*D15)/4)*2) -> 1000 | F15: =SUM(E15*B3) -> 50 | G15: =SUM(E15/2) -> 500 | H15: 0.06 | I15: =SUM(G15*H15) -> 30 | J15: 0 | K15: 0 | L15: 0 | M15: 0 | N15: 0 | O15: =SUM(F15+I15+J15+K15+L15+M15+N15) -> 80 | Q15: 2 | R15: =SUM((O15*Q15)+O15) -> 240 | S15: =SUM(R15/C15) -> 0.48 | T15: PREÇO UNIT. FINAL
A16: VERDASCA | B16: MIOLO BROCHURA PAV. PAPEL 150 GRS | C16: 500 | D16: 48 | E16: =SUM(((C16*D16)/4)*2) -> 12000 | F16: =SUM(E16*B3) -> 600 | G16: =SUM(E16/2) -> 6000 | H16: 0.06 | I16: =SUM(G16*H16) -> 360 | J16: 10 | K16: 0 | L16: 0 | M16: 5.12 | N16: 0 | O16: =SUM(F16+I16+J16+K16+L16+M16+N16) -> 975.12 | Q16: 3 | R16: =SUM((O16*Q16)+O16) -> 3900.48 | S16: =SUM(R16/C16) -> 7.80096 | T16: =SUM(S15+S16) -> 8.28096
A18: VERDASCA | B18: CAPA BROCHURA EST. PAPEL 250 GRS | C18: 500 | D18: 4 | E18: =SUM(((C18*D18)/4)*2) -> 1000 | F18: =SUM(E18*B3) -> 50 | G18: =SUM(E18/2) -> 500 | H18: 0.11 | I18: =SUM(G18*H18) -> 55 | J18: 0 | K18: 0 | L18: 0 | M18: 0 | N18: 0 | O18: =SUM(F18+I18+J18+K18+L18+M18+N18) -> 105 | Q18: 1.5 | R18: =SUM((O18*Q18)+O18) -> 262.5 | S18: =SUM(R18/C18) -> 0.525 | T18: PREÇO UNIT. FINAL
A19: VERDASCA | B19: MIOLO BROCHURA EST. PAPEL 150 GRS | C19: 500 | D19: 48 | E19: =SUM(((C19*D19)/4)*2) -> 12000 | F19: =SUM(E19*B3) -> 600 | G19: =SUM(E19/2) -> 6000 | H19: 0.06 | I19: =SUM(G19*H19) -> 360 | J19: 44 | K19: 0 | L19: 0 | M19: 5.12 | N19: 0 | O19: =SUM(F19+I19+J19+K19+L19+M19+N19) -> 1009.12 | Q19: 1.5 | R19: =SUM((O19*Q19)+O19) -> 2522.8 | S19: =SUM(R19/C19) -> 5.0456 | T19: =SUM(S18+S19) -> 5.5706
A21: VERDASCA | B21: CAPA FACHADA PAPEL 250 GRS | C21: 500 | D21: 4 | E21: =SUM(((C21*D21)/4)*2) -> 1000 | F21: =SUM(E21*B3) -> 50 | G21: =SUM(E21/2) -> 500 | H21: 0.11 | I21: =SUM(G21*H21) -> 55 | J21: 0 | K21: 0 | L21: 0 | M21: 0 | N21: 0 | O21: =SUM(F21+I21+J21+K21+L21+M21+N21) -> 105 | Q21: 1.5 | R21: =SUM((O21*Q21)+O21) -> 262.5 | S21: =SUM(R21/C21) -> 0.525 | T21: PREÇO UNIT. FINAL
A22: VERDASCA | B22: MIOLO FACHADA EST. PAPEL 150 GRS | C22: 500 | D22: 48 | E22: =SUM(((C22*D22)/4)*2) -> 12000 | F22: =SUM(E22*B3) -> 600 | G22: =SUM(E22/2) -> 6000 | H22: 0.06 | I22: =SUM(G22*H22) -> 360 | J22: 44 | K22: 0 | L22: 0 | M22: 5.12 | N22: 0 | O22: =SUM(F22+I22+J22+K22+L22+M22+N22) -> 1009.12 | Q22: 1.5 | R22: =SUM((O22*Q22)+O22) -> 2522.8 | S22: =SUM(R22/C22) -> 5.0456 | T22: =SUM(S21+S22) -> 5.5706
A24: PETFILLING | B24: REVISTA GUIA DE GATINHO 100x210. 150grs | C24: 300 | D24: 28 | E24: =SUM(((C24*D24)/4)*2) -> 4200 | F24: =SUM(E24*B3) -> 210 | G24: =SUM(E24/2) -> 2100 | H24: 0.06 | I24: =SUM(G24*H24) -> 126 | J24: 15 | K24: 0 | L24: 0 | M24: 105 | N24: 0 | O24: =SUM(F24+I24+J24+K24+L24+M24+N24) -> 456 | Q24: 2 | R24: =SUM((O24*Q24)+O24) -> 1368 | S24: =SUM(R24/C24) -> 4.56
A26: PETFILLING | B26: REVISTA MANUAL CACHORO 100x210. 170grs | C26: 250 | D26: 44 | E26: =SUM(((C26*D26)/4)*2) -> 5500 | F26: =SUM(E26*B3) -> 275 | G26: =SUM(E26/2) -> 2750 | H26: 0.073 | I26: =SUM(G26*H26) -> 200.75 | J26: 15 | K26: 0 | L26: 0 | M26: 87.5 | N26: 0 | O26: =SUM(F26+I26+J26+K26+L26+M26+N26) -> 578.25 | Q26: 2 | R26: =SUM((O26*Q26)+O26) -> 1734.75 | S26: =SUM(R26/C26) -> 6.939
A28: EFICACIA | B28: CAPA BROCHURA Eficacia PAPEL 250 GRS | C28: 1000 | D28: 4 | E28: =SUM(((C28*D28)/4)*2) -> 2000 | F28: =SUM(E28*B3) -> 100 | G28: =SUM(E28/2) -> 1000 | H28: 0.11 | I28: =SUM(G28*H28) -> 110 | J28: 0 | K28: 0 | L28: 0 | M28: 0 | N28: 0 | O28: =SUM(F28+I28+J28+K28+L28+M28+N28) -> 210 | P28: =O28/C28 -> 0.21 | Q28: 2 | R28: =SUM((O28*Q28)+O28) -> 630 | S28: =SUM(R28/C28) -> 0.63 | T28: PREÇO UNIT. FINAL
A29: EFICACIA | B29: MIOLO BROCHURA Eficacia PAPEL 150 GRS | C29: 1000 | D29: 32 | E29: =SUM(((C29*D29)/4)*2) -> 16000 | F29: =SUM(E29*B3) -> 800 | G29: =SUM(E29/2) -> 8000 | H29: 0.06 | I29: =SUM(G29*H29) -> 480 | J29: 44 | K29: 170 | L29: 0 | M29: 10.23 | N29: 0 | O29: =SUM(F29+I29+J29+K29+L29+M29+N29) -> 1504.23 | P29: =O29/C29 -> 1.50423 | Q29: 2 | R29: =SUM((O29*Q29)+O29) -> 4512.69 | S29: =SUM(R29/C29) -> 4.51269 | T29: =SUM(S28+S29) -> 5.14269
A30: EFICACIA | B30: CAPA BROCHURA Eficacia PAPEL 350 GRS | C30: 250 | D30: 4 | E30: =SUM(((C30*D30)/4)*2) -> 500 | F30: =SUM(E30*B3) -> 25 | G30: =SUM(E30/2) -> 250 | H30: 0.09 | I30: =SUM(G30*H30) -> 22.5 | J30: 0 | K30: 0 | L30: 0 | M30: 0 | N30: 0 | O30: =SUM(F30+I30+J30+K30+L30+M30+N30) -> 47.5 | P30: =O30/C30 -> 0.19 | Q30: 1.5 | R30: =SUM((O30*Q30)+O30) -> 118.75 | S30: =SUM(R30/C30) -> 0.475 | T30: PREÇO UNIT. FINAL
A31: EFICACIA | B31: MIOLO BROCHURA Eficacia PAPEL 150 GRS | C31: 250 | D31: 54 | E31: =SUM(((C31*D31)/4)*2) -> 6750 | F31: =SUM(E31*B3) -> 337.5 | G31: =SUM(E31/2) -> 3375 | H31: 0.06 | I31: =SUM(G31*H31) -> 202.5 | J31: 15 | K31: 0 | L31: 0 | M31: 2.56 | N31: 0 | O31: =SUM(F31+I31+J31+K31+L31+M31+N31) -> 557.56 | P31: =O31/C31 -> 2.23024 | Q31: 1.5 | R31: =SUM((O31*Q31)+O31) -> 1393.9 | S31: =SUM(R31/C31) -> 5.5756 | T31: =SUM(S30+S31) -> 6.0506
A33: SODARCA | B33: CAPA BROCHURA Eficacia PAPEL 350 GRS | C33: 500 | D33: 4 | E33: =SUM(((C33*D33)/4)*2) -> 1000 | F33: =SUM(E33*B3) -> 50 | G33: =SUM(E33/2) -> 500 | H33: 0.095 | I33: =SUM(G33*H33) -> 47.5 | J33: 0 | K33: 0 | L33: 0 | M33: 0 | N33: 0 | O33: =SUM(F33+I33+J33+K33+L33+M33+N33) -> 97.5 | P33: =O33/C33 -> 0.195 | Q33: 2 | R33: =SUM((O33*Q33)+O33) -> 292.5 | S33: =SUM(R33/C33) -> 0.585 | T33: PREÇO UNIT. FINAL
A34: SODARCA | B34: MIOLO BROCHURA Eficacia PAPEL 140 GRS | C34: 500 | D34: 20 | E34: =SUM(((C34*D34)/4)*2) -> 5000 | F34: =SUM(E34*B3) -> 250 | G34: =SUM(E34/2) -> 2500 | H34: 0.21 | I34: =SUM(G34*H34) -> 525 | J34: 44 | K34: 0 | L34: 0 | M34: 10.23 | N34: 0 | O34: =SUM(F34+I34+J34+K34+L34+M34+N34) -> 829.23 | P34: =O34/C34 -> 1.65846 | Q34: 2 | R34: =SUM((O34*Q34)+O34) -> 2487.69 | S34: =SUM(R34/C34) -> 4.97538 | T34: =SUM(S33+S34) -> 5.56038
A36: pineforest | B36: diptico em papel 150g | C36: 1000 | D36: 4 | E36: =SUM(((C36*D36)/4)*2) -> 2000 | F36: =SUM(E36*B3) -> 100 | G36: =SUM(E36/2) -> 1000 | H36: 0.06 | I36: =SUM(G36*H36) -> 60 | J36: 44 | K36: 0 | L36: 0 | M36: 225 | N36: 0 | O36: =SUM(F36+I36+J36+K36+L36+M36+N36) -> 429 | P36: =O36/C36 -> 0.429 | Q36: 0.5 | R36: =SUM((O36*Q36)+O36) -> 643.5 | S36: =SUM(R36/C36) -> 0.6435 | T36: PREÇO UNIT. FINAL
A37: soudias | B37: diptico em papel 150g | C37: 1000 | D37: 4 | E37: =SUM(((C37*D37)/4)*2) -> 2000 | F37: =SUM(E37*B3) -> 100 | G37: =SUM(E37/2) -> 1000 | H37: 0.06 | I37: =SUM(G37*H37) -> 60 | J37: 44 | K37: 0 | L37: 0 | M37: 225 | N37: 0 | O37: =SUM(F37+I37+J37+K37+L37+M37+N37) -> 429 | P37: =O37/C37 -> 0.429 | Q37: 0.5 | R37: =SUM((O37*Q37)+O37) -> 643.5 | S37: =SUM(R37/C37) -> 0.6435 | T37: =SUM(S36+S37) -> 1.287
A39: missal | B39: missal | C39: 80 | D39: 16 | E39: =SUM(((C39*D39)/4)*2) -> 640 | F39: =SUM(E39*B3) -> 32 | G39: =SUM(E39/2) -> 320 | H39: 0.06 | I39: =SUM(G39*H39) -> 19.2 | J39: 20 | K39: 0 | L39: 0 | M39: 0.51 | N39: 0 | O39: =SUM(F39+I39+J39+K39+L39+M39+N39) -> 71.71 | P39: =O39/C39 -> 0.896375 | Q39: 2 | R39: =SUM((O39*Q39)+O39) -> 215.13 | S39: =SUM(R39/C39) -> 2.689125 | T39: =SUM(S38+S39) -> 2.689125
A41: artma | B41: CAPA BROCHURA Eficacia PAPEL 300 GRS | C41: 500 | D41: 4 | E41: =SUM(((C41*D41)/4)*2) -> 1000 | F41: =SUM(E41*B11) -> 150 | G41: =SUM(E41/2) -> 500 | H41: 0.09 | I41: =SUM(G41*H41) -> 45 | J41: 0 | K41: 0 | L41: 0 | M41: 0 | N41: 0 | O41: =SUM(F41+I41+J41+K41+L41+M41+N41) -> 195 | P41: =O41/C41 -> 0.39 | Q41: 2 | R41: =SUM((O41*Q41)+O41) -> 585 | S41: =SUM(R41/C41) -> 1.17 | T41: PREÇO UNIT. FINAL
A42: artma | B42: MIOLO BROCHURA PAPEL 150 GRS | C42: 500 | D42: 12 | E42: =SUM(((C42*D42)/4)*2) -> 3000 | F42: =SUM(E42*B11) -> 450 | G42: =SUM(E42/2) -> 1500 | H42: 0.06 | I42: =SUM(G42*H42) -> 90 | J42: 44 | K42: 0 | L42: 0 | M42: 5.12 | N42: 0 | O42: =SUM(F42+I42+J42+K42+L42+M42+N42) -> 589.12 | P42: =O42/C42 -> 1.17824 | Q42: 2 | R42: =SUM((O42*Q42)+O42) -> 1767.36 | S42: =SUM(R42/C42) -> 3.53472 | T42: =SUM(S41+S42) -> 4.70472 | U42: =R42+R41 -> 2352.36
A44: DJANIRA MONTALVAO DA LUZ | B44: CAPA Livro | C44: 1 | D44: 4 | E44: =SUM(((C44*D44)/4)*2) -> 2 | F44: =SUM(E44*B9) -> 1 | G44: =SUM(E44/2) -> 1 | H44: 0.09 | I44: =SUM(G44*H44) -> 0.09 | J44: 0 | K44: 0 | L44: 0 | M44: 0 | N44: 0 | O44: =SUM(F44+I44+J44+K44+L44+M44+N44) -> 1.09 | P44: =O44/C44 -> 1.09 | Q44: 3 | R44: =SUM((O44*Q44)+O44) -> 4.36 | S44: =SUM(R44/C44) -> 4.36 | T44: PREÇO UNIT. FINAL
A45: DJANIRA MONTALVAO DA LUZ | B45: MIOLO | C45: 50 | D45: 136 | E45: =SUM(((C45*D45)/4)*2) -> 3400 | F45: =SUM(E45*B3) -> 170 | G45: =SUM(E45/2) -> 1700 | H45: 0.06 | I45: =SUM(G45*H45) -> 102 | J45: 15 | K45: 0 | L45: 0 | M45: 17.5 | N45: 17.5 | O45: =SUM(F45+I45+J45+K45+L45+M45+N45) -> 322 | P45: =O45/C45 -> 6.44 | Q45: 3 | R45: =SUM((O45*Q45)+O45) -> 1288 | S45: =SUM(R45/C45) -> 25.76 | T45: =SUM(S44+S45) -> 30.12
A47: Joana | B47: CAPA Livro | C47: 50 | D47: 2 | E47: =SUM(((C47*D47)/4)*2) -> 50 | F47: =SUM(E47*B3) -> 2.5 | G47: =SUM(E47/2) -> 25 | H47: 0.06 | I47: =SUM(G47*H47) -> 1.5 | J47: 0 | K47: 0 | L47: 0 | M47: 0 | N47: 0 | O47: =SUM(F47+I47+J47+K47+L47+M47+N47) -> 4 | P47: =O47/C47 -> 0.08 | Q47: 1.2 | R47: =SUM((O47*Q47)+O47) -> 8.8 | S47: =SUM(R47/C47) -> 0.176 | T47: PREÇO UNIT. FINAL
A48: Joana | B48: MIOLO | C48: 50 | D48: 8 | E48: =SUM(((C48*D48)/4)*2) -> 200 | F48: =SUM(E48*B3) -> 10 | G48: =SUM(E48/2) -> 100 | H48: 0.06 | I48: =SUM(G48*H48) -> 6 | J48: 5 | K48: 0 | L48: 0 | M48: 0 | N48: 0 | O48: =SUM(F48+I48+J48+K48+L48+M48+N48) -> 21 | P48: =O48/C48 -> 0.42 | Q48: 1 | R48: =SUM((O48*Q48)+O48) -> 42 | S48: =SUM(R48/C48) -> 0.84 | T48: =SUM(S47+S48) -> 1.016
A49: Tiago Trail | B49: curriculo | C49: 10 | D49: 10 | E49: =SUM(((C49*D49)/4)*2) -> 50 | F49: =SUM(E49*B4) -> 6 | G49: =SUM(E49/2) -> 25 | H49: 0.09 | I49: =SUM(G49*H49) -> 2.25 | J49: 5 | K49: 0 | L49: 0 | M49: 0 | N49: 0 | O49: =SUM(F49+I49+J49+K49+L49+M49+N49) -> 13.25 | P49: =O49/C49 -> 1.325 | Q49: 3 | R49: =SUM((O49*Q49)+O49) -> 53 | S49: =SUM(R49/C49) -> 5.3 | T49: =SUM(S48+S49) -> 6.14
A51: HARMA | B51: CAPA Livro | C51: 2 | D51: 4 | E51: =SUM(((C51*D51)/4)*2) -> 4 | F51: =SUM(E51*B3) -> 0.2 | G51: =SUM(E51/2) -> 2 | H51: 0.14 | I51: =SUM(G51*H51) -> 0.28 | J51: 0 | K51: 0 | L51: 0 | M51: 0 | N51: 0 | O51: =SUM(F51+I51+J51+K51+L51+M51+N51) -> 0.48 | P51: =O51/C51 -> 0.24 | Q51: 3 | R51: =SUM((O51*Q51)+O51) -> 1.92 | S51: =SUM(R51/C51) -> 0.96 | T51: PREÇO UNIT. FINAL
A52: HARMA | B52: MIOLO | C52: 2 | D52: 12 | E52: =SUM(((C52*D52)/4)*2) -> 12 | F52: =SUM(E52*B4) -> 1.44 | G52: =SUM(E52/2) -> 6 | H52: 0.06 | I52: =SUM(G52*H52) -> 0.36 | J52: 5 | K52: 0 | L52: 0 | M52: 0 | N52: 0 | O52: =SUM(F52+I52+J52+K52+L52+M52+N52) -> 6.8 | P52: =O52/C52 -> 3.4 | Q52: 3 | R52: =SUM((O52*Q52)+O52) -> 27.2 | S52: =SUM(R52/C52) -> 13.6 | T52: =SUM(S51+S52)/C52 -> 7.28
A54: Sr. Gustavo | B54: CAPA Livro | C54: 100 | D54: 4 | E54: =SUM(((C54*D54)/4)*2) -> 200 | F54: =SUM(E54*B3) -> 10 | G54: =SUM(E54/2) -> 100 | H54: 0.09 | I54: =SUM(G54*H54) -> 9 | J54: 0 | K54: 50 | L54: 0 | M54: 0 | N54: 0 | O54: =SUM(F54+I54+J54+K54+L54+M54+N54) -> 69 | P54: =O54/C54 -> 0.69 | Q54: 2 | R54: =SUM((O54*Q54)+O54) -> 207 | S54: =SUM(R54/C54) -> 2.07 | T54: PREÇO UNIT. FINAL
B55: MIOLO | C55: 100 | D55: 20 | E55: =SUM(((C55*D55)/4)*2) -> 1000 | F55: =SUM(E55*B3) -> 50 | G55: =SUM(E55/2) -> 500 | H55: 0.06 | I55: =SUM(G55*H55) -> 30 | J55: 15 | K55: 0 | L55: 0 | M55: 2.05 | N55: 0 | O55: =SUM(F55+I55+J55+K55+L55+M55+N55) -> 97.05 | P55: =O55/C55 -> 0.9705 | Q55: 2 | R55: =SUM((O55*Q55)+O55) -> 291.15 | S55: =SUM(R55/C55) -> 2.9115 | T55: =SUM(S54+S55) -> 4.9815
A57: SOHNIV | B57: CAPA BROCHURA PAV. PAPEL 250 GRS | C57: 100 | D57: 4 | E57: =SUM(((C57*D57)/4)*2) -> 200 | F57: =SUM(E57*B3) -> 10 | G57: =SUM(E57/2) -> 100 | H57: 0.06 | I57: =SUM(G57*H57) -> 6 | J57: 0 | K57: 0 | L57: 0 | M57: 0 | N57: 0 | O57: =SUM(F57+I57+J57+K57+L57+M57+N57) -> 16 | P57: =O57/C57 -> 0.16 | Q57: 2 | R57: =SUM((O57*Q57)+O57) -> 48 | S57: =SUM(R57/C57) -> 0.48 | T57: PREÇO UNIT. FINAL
B58: MIOLO BROCHURA PAV. PAPEL 150 GRS | C58: 100 | D58: 4 | E58: =SUM(((C58*D58)/4)*2) -> 200 | F58: =SUM(E58*B3) -> 10 | G58: =SUM(E58/2) -> 100 | H58: 0.06 | I58: =SUM(G58*H58) -> 6 | J58: 10 | K58: 0 | L58: 0 | M58: 5.12 | N58: 0 | O58: =SUM(F58+I58+J58+K58+L58+M58+N58) -> 31.12 | P58: =O58/C58 -> 0.3112 | Q58: 2 | R58: =SUM((O58*Q58)+O58) -> 93.36 | S58: =SUM(R58/C58) -> 0.9336 | T58: =SUM(S57+S58) -> 1.4136
A60: BRUNO | B60: CAPA BROCHURA PAV. PAPEL 250 GRS | C60: 1 | D60: 4 | E60: =SUM(((C60*D60)/4)*2) -> 2 | F60: =SUM(E60*B3) -> 0.1 | G60: =SUM(E60/2) -> 1 | H60: 0.09 | I60: =SUM(G60*H60) -> 0.09 | J60: 0 | K60: 0 | L60: 0 | M60: 0 | N60: 0 | O60: =SUM(F60+I60+J60+K60+L60+M60+N60) -> 0.19 | P60: =O60/C60 -> 0.19 | Q60: 2 | R60: =SUM((O60*Q60)+O60) -> 0.57 | S60: =SUM(R60/C60) -> 0.57 | T60: PREÇO UNIT. FINAL
B61: MIOLO BROCHURA PAV. PAPEL 150 GRS | C61: 1 | D61: 36 | E61: =SUM(((C61*D61)/4)*2) -> 18 | F61: =SUM(E61*B3) -> 0.9 | G61: =SUM(E61/2) -> 9 | H61: 0.09 | I61: =SUM(G61*H61) -> 0.81 | J61: 5 | K61: 0 | L61: 0 | M61: 0 | N61: 0 | O61: =SUM(F61+I61+J61+K61+L61+M61+N61) -> 6.71 | P61: =O61/C61 -> 6.71 | Q61: 0.4 | R61: =SUM((O61*Q61)+O61) -> 9.394 | S61: =SUM(R61/C61) -> 9.394 | T61: =SUM(S60+S61) -> 9.964
A63: BRUNO | E63: =SUM(((C63*D63)/4)*2) -> 0 | F63: =SUM(E63*B3) -> 0 | G63: =SUM(E63/2) -> 0 | H63: 0 | I63: =SUM(G63*H63) -> 0 | J63: 0 | K63: 0 | L63: 0 | M63: 0 | N63: 0 | O63: =SUM(F63+I63+J63+K63+L63+M63+N63) -> 0 | P63: =O63/C63 -> #DIV/0! | Q63: 2 | R63: =SUM((O63*Q63)+O63) -> 0 | S63: =SUM(R63/C63) -> #DIV/0! | T63: PREÇO UNIT. FINAL
B64: MIOLO BROCHURA PAV. PAPEL 150 GRS | C64: 10 | D64: 32 | E64: =SUM(((C64*D64)/4)*2) -> 160 | F64: =SUM(E64*B3) -> 8 | G64: =SUM(E64/2) -> 80 | H64: 0.06 | I64: =SUM(G64*H64) -> 4.8 | J64: 5 | K64: 0 | L64: 0 | M64: 0 | N64: 0 | O64: =SUM(F64+I64+J64+K64+L64+M64+N64) -> 17.8 | P64: =O64/C64 -> 1.78 | Q64: 3 | R64: =SUM((O64*Q64)+O64) -> 71.2 | S64: =SUM(R64/C64) -> 7.12 | T64: =SUM(S63+S64) -> #DIV/0!
A66: ROTA e SILVA | E66: =SUM(((C66*D66)/4)*2) -> 0 | F66: =SUM(E66*B6) -> 0 | G66: =SUM(E66/2) -> 0 | H66: 0 | I66: =SUM(G66*H66) -> 0 | J66: 0 | K66: 0 | L66: 0 | M66: 0 | N66: 0 | O66: =SUM(F66+I66+J66+K66+L66+M66+N66) -> 0 | P66: =O66/C66 -> #DIV/0! | Q66: 2 | R66: =SUM((O66*Q66)+O66) -> 0 | S66: =SUM(R66/C66) -> #DIV/0! | T66: PREÇO UNIT. FINAL
B67: MIOLO BROCHURA PAV. PAPEL 150 GRS | C67: 11 | D67: 32 | E67: =SUM(((C67*D67)/4)*2) -> 176 | F67: 0.05 | G67: =SUM(E67/2) -> 88 | H67: 0.06 | I67: =SUM(G67*H67) -> 5.28 | J67: 5 | K67: 0 | L67: 0 | M67: 0.23 | N67: 0 | O67: =SUM(F67+I67+J67+K67+L67+M67+N67) -> 10.56 | P67: =O67/C67 -> 0.96 | Q67: 3 | R67: =SUM((O67*Q67)+O67) -> 42.24 | S67: =SUM(R67/C67) -> 3.84 | T67: =SUM(S66+S67) -> #DIV/0!
A69: PERCENTRO | C69: 0 | D69: 0 | E69: =SUM(((C69*D69)/4)*2) -> 0 | F69: 0.5 | G69: =SUM(E69/2) -> 0 | H69: 0 | I69: =SUM(G69*H69) -> 0 | J69: 0 | K69: 0 | L69: 0 | M69: 0 | N69: 0 | O69: =SUM(F69+I69+J69+K69+L69+M69+N69) -> 0.5 | P69: =O69/C69 -> #DIV/0! | Q69: 2 | R69: =SUM((O69*Q69)+O69) -> 1.5 | S69: =SUM(R69/C69) -> #DIV/0! | T69: PREÇO UNIT. FINAL
B70: MIOLO BROCHURA PAV. PAPEL 150 GRS | C70: 50 | D70: 12 | E70: =SUM(((C70*D70)/4)*2) -> 300 | F70: 0.05 | G70: =SUM(E70/2) -> 150 | H70: 0.09 | I70: =SUM(G70*H70) -> 13.5 | J70: 15 | K70: 25 | L70: 0 | M70: 1.02 | N70: 0 | O70: =SUM(F70+I70+J70+K70+L70+M70+N70) -> 54.57 | P70: =O70/C70 -> 1.0914 | Q70: 2 | R70: =SUM((O70*Q70)+O70) -> 163.71 | S70: =SUM(R70/C70) -> 3.2742 | T70: =SUM(S69+S70) -> #DIV/0!
A72: Aguas centro Litorall | B72: capa | C72: 125 | D72: 4 | E72: =SUM(((C72*D72)/4)*2) -> 250 | F72: 0.05 | G72: =SUM(E72/2) -> 125 | H72: 0.09 | I72: =SUM(G72*H72) -> 11.25 | J72: 0 | K72: 62.5 | L72: 0 | M72: 0 | N72: 0 | O72: =SUM(F72+I72+J72+K72+L72+M72+N72) -> 73.8 | P72: =O72/C72 -> 0.5904 | Q72: 2 | R72: =SUM((O72*Q72)+O72) -> 221.4 | S72: =SUM(R72/C72) -> 1.7712 | T72: PREÇO UNIT. FINAL
B73: MIOLO BROCHURA PAV. PAPEL ior 90 | C73: 125 | D73: 208 | E73: =SUM(((C73*D73)/4)*2) -> 13000 | F73: 0.05 | G73: =SUM(E73/2) -> 6500 | H73: 0.03 | I73: =SUM(G73*H73) -> 195 | J73: 25 | K73: 0 | L73: 0 | M73: 0.23 | N73: 43.75 | O73: =SUM(F73+I73+J73+K73+L73+M73+N73) -> 264.03 | P73: =O73/C73 -> 2.11224 | Q73: 2 | R73: =SUM((O73*Q73)+O73) -> 792.09 | S73: =SUM(R73/C73) -> 6.33672 | T73: =SUM(S72+S73) -> 8.10792 | U73: =SUM(P72+P73) -> 2.70264
A74: Aguas centro Litorall | B74: capa | C74: 250 | D74: 4 | E74: =SUM(((C74*D74)/4)*2) -> 500 | F74: 0.05 | G74: =SUM(E74/2) -> 250 | H74: 0.09 | I74: =SUM(G74*H74) -> 22.5 | J74: 0 | K74: 85 | L74: 0 | M74: 0 | N74: 0 | O74: =SUM(F74+I74+J74+K74+L74+M74+N74) -> 107.55 | P74: =O74/C74 -> 0.4302 | Q74: 2 | R74: =SUM((O74*Q74)+O74) -> 322.65 | S74: =SUM(R74/C74) -> 1.2906 | T74: PREÇO UNIT. FINAL
B75: MIOLO BROCHURA PAV. PAPEL ior 90 | C75: 250 | D75: 128 | E75: =SUM(((C75*D75)/4)*2) -> 16000 | F75: 0.05 | G75: =SUM(E75/2) -> 8000 | H75: 0.03 | I75: =SUM(G75*H75) -> 240 | J75: 25 | K75: 0 | L75: 0 | M75: 0.23 | N75: 87.5 | O75: =SUM(F75+I75+J75+K75+L75+M75+N75) -> 352.78 | P75: =O75/C75 -> 1.41112 | Q75: 2 | R75: =SUM((O75*Q75)+O75) -> 1058.34 | S75: =SUM(R75/C75) -> 4.23336 | T75: =SUM(S74+S75) -> 5.52396 | U75: =SUM(P74+P75) -> 1.84132
A77: concurso wmg | B77: capa | C77: 100 | D77: 4 | E77: =SUM(((C77*D77)/4)*2) -> 200 | F77: 0.05 | G77: =SUM(E77/2) -> 100 | H77: 0.09 | I77: =SUM(G77*H77) -> 9 | J77: 0 | K77: 50 | L77: 0 | M77: 0 | N77: 0 | O77: =SUM(F77+I77+J77+K77+L77+M77+N77) -> 59.05 | P77: =O77/C77 -> 0.5905 | Q77: 2 | R77: =SUM((O77*Q77)+O77) -> 177.15 | S77: =SUM(R77/C77) -> 1.7715 | T77: PREÇO UNIT. FINAL
B78: MIOLO BROCHURA PAV. PAPEL ior 90 | C78: 100 | D78: 20 | E78: =SUM(((C78*D78)/4)*2) -> 1000 | F78: 0.05 | G78: =SUM(E78/2) -> 500 | H78: 0.03 | I78: =SUM(G78*H78) -> 15 | J78: 25 | K78: 0 | L78: 0 | M78: 0.23 | N78: 43.75 | O78: =SUM(F78+I78+J78+K78+L78+M78+N78) -> 84.03 | P78: =O78/C78 -> 0.8403 | Q78: 2 | R78: =SUM((O78*Q78)+O78) -> 252.09 | S78: =SUM(R78/C78) -> 2.5209 | T78: =SUM(S77+S78) -> 4.2924 | U78: =SUM(P77+P78) -> 1.4308
A80: concurso laminam | B80: capa | C80: 20 | D80: 4 | E80: =SUM(((C80*D80)/4)*2) -> 40 | F80: 0.06 | G80: =SUM(E80/2) -> 20 | H80: 0.09 | I80: =SUM(G80*H80) -> 1.8 | J80: 0 | K80: 10 | L80: 25 | M80: 0 | N80: 10 | O80: =SUM(F80+I80+J80+K80+L80+M80+N80) -> 46.86 | P80: =O80/C80 -> 2.343 | Q80: 2 | R80: =SUM((O80*Q80)+O80) -> 140.58 | S80: =SUM(R80/C80) -> 7.029 | T80: PREÇO UNIT. FINAL
B81: MIOLO BROCHURA PAV. PAPEL 150 | C81: 20 | D81: 32 | E81: =SUM(((C81*D81)/4)*2) -> 320 | F81: 0.06 | G81: =SUM(E81/2) -> 160 | H81: 0.03 | I81: =SUM(G81*H81) -> 4.8 | J81: 25 | K81: 0 | L81: 0 | M81: 0.23 | N81: 43.75 | O81: =SUM(F81+I81+J81+K81+L81+M81+N81) -> 73.84 | P81: =O81/C81 -> 3.692 | Q81: 2 | R81: =SUM((O81*Q81)+O81) -> 221.52 | S81: =SUM(R81/C81) -> 11.076 | T81: =SUM(S80+S81) -> 18.105 | U81: =SUM(P80+P81) -> 6.035
A83: SILACO | B83: capa | C83: 500 | D83: 4 | E83: =SUM(((C83*D83)/4)*2) -> 1000 | F83: 0.06 | G83: =SUM(E83/2) -> 500 | H83: 0.09 | I83: =SUM(G83*H83) -> 45 | J83: 0 | K83: 10 | L83: 250 | M83: 0 | N83: 0 | O83: =SUM(F83+I83+J83+K83+L83+M83+N83) -> 305.06 | P83: =O83/C83 -> 0.61012 | Q83: 3 | R83: =SUM((O83*Q83)+O83) -> 1220.24 | S83: =SUM(R83/C83) -> 2.44048 | T83: PREÇO UNIT. FINAL
B84: MIOLO BROCHURA PAV. PAPEL 150 | C84: 500 | D84: 22 | E84: =SUM(((C84*D84)/4)*2) -> 5500 | F84: 0.06 | G84: =SUM(E84/2) -> 2750 | H84: 0.06 | I84: =SUM(G84*H84) -> 165 | J84: 176 | K84: 85 | L84: 0 | M84: 10.23 | N84: 75 | O84: =SUM(F84+I84+J84+K84+L84+M84+N84) -> 511.29 | P84: =O84/C84 -> 1.02258 | Q84: 3 | R84: =SUM((O84*Q84)+O84) -> 2045.16 | S84: =SUM(R84/C84) -> 4.09032 | T84: =SUM(S83+S84) -> 6.5308 | U84: =SUM(P83+P84) -> 1.6327
A85: SILACO | B85: capa | C85: 1000 | D85: 4 | E85: =SUM(((C85*D85)/4)*2) -> 2000 | F85: 0.06 | G85: =SUM(E85/2) -> 1000 | H85: 0.09 | I85: =SUM(G85*H85) -> 90 | J85: 0 | K85: 10 | L85: 500 | M85: 0 | N85: 0 | O85: =SUM(F85+I85+J85+K85+L85+M85+N85) -> 600.06 | P85: =O85/C85 -> 0.60006 | Q85: 3 | R85: =SUM((O85*Q85)+O85) -> 2400.24 | S85: =SUM(R85/C85) -> 2.40024 | T85: PREÇO UNIT. FINAL
B86: MIOLO BROCHURA PAV. PAPEL 150 | C86: 1000 | D86: 22 | E86: =SUM(((C86*D86)/4)*2) -> 11000 | F86: 0.06 | G86: =SUM(E86/2) -> 5500 | H86: 0.06 | I86: =SUM(G86*H86) -> 330 | J86: 176 | K86: 85 | L86: 0 | M86: 20.46 | N86: 150 | O86: =SUM(F86+I86+J86+K86+L86+M86+N86) -> 761.52 | P86: =O86/C86 -> 0.76152 | Q86: 3 | R86: =SUM((O86*Q86)+O86) -> 3046.08 | S86: =SUM(R86/C86) -> 3.04608 | T86: =SUM(S85+S86) -> 5.44632 | U86: =SUM(P85+P86) -> 1.36158

Sheet IMP. GRANDE FORMATO
A1: IMPRESSÃO | B1: FORNECEDOR | C1: Preço m2 | D1: Quant. m2 | E1: Quantidade por m2 para manter preço | F1: CUSTO PRODUÇÃO | G1: % LUCRO | H1: TOTAL
A2: Caixas de Luz | B2: Leiripantone | C2: 25 | D2: 2 | E2: 2 | F2: =SUM(E2*C2) -> 50 | G2: 0.2 | H2: =SUM((F2*G2)+F2) -> 60 | J2: MÃO OBRA - 22€ / HORA
A3: Impressão de Lona | B3: NHM | C3: 16 | D3: 2 | E3: 10.5 | F3: =SUM(E3*C3) -> 168 | G3: 0.4 | H3: =SUM((F3*G3)+F3) -> 235.2
A4: Vinil Microperfurado Impresso | B4: NHM | C4: 22 | D4: 0 | E4: 0 | F4: =SUM(E4*C4) -> 0 | G4: 0.4 | H4: =SUM((F4*G4)+F4) -> 0
A5: Impressão de Lona | B5: BE EXPO. | C5: 15 | D5: 9 | E5: 9 | F5: =SUM(E5*C5) -> 135 | G5: 0.4 | H5: =SUM((F5*G5)+F5) -> 189
A6: Tela para Roll Up | B6: Leiripantone | C6: 30 | D6: 1 | E6: 1 | F6: =SUM(E6*C6) -> 30 | G6: 0.4 | H6: =SUM((F6*G6)+F6) -> 42
A7: Vinil para Balcao Painel Track com Laminação Mate | B7: Leiripantone | C7: 24 | D7: 2 | E7: 4 | F7: =SUM(E7*C7) -> 96 | G7: 0.4 | H7: =SUM((F7*G7)+F7) -> 134.4
A8: DTF | B8: Leiripantone | C8: 15 | D8: 2 | E8: 2 | F8: =SUM(E8*C8) -> 30 | G8: 0.4 | H8: =SUM((F8*G8)+F8) -> 42
A9: Caixas de Luz | B9: Publifast | C9: 27.65 | D9: 0.75 | E9: 0.75 | F9: =SUM(E9*C9) -> 20.7375 | G9: 0.2 | H9: =SUM((F9*G9)+F9) -> 24.885
A10: Impressão de papel em plotter | B10: Leiripantone | C10: 15 | D10: 0.274 | E10: 0.99 | F10: =SUM(E10*C10) -> 14.85 | G10: 0.4 | H10: =SUM((F10*G10)+F10) -> 20.79
A11: Impressão de papel em plotter 1,5m | B11: NHM | C11: 12 | D11: 0.5 | E11: 0.6 | F11: =SUM(E11*C11) -> 7.2 | G11: 0.4 | H11: =SUM((F11*G11)+F11) -> 10.08
A12: Impressção Vinil UV | B12: Leiripantone | C12: 12 | D12: 2 | E12: 1.644 | F12: =SUM(E12*C12) -> 19.728 | G12: 0.4 | H12: =SUM((F12*G12)+F12) -> 27.6192
A13: Impressção Vinil | B13: Leiripantone | C13: 10 | D13: 2 | E13: 2 | F13: =SUM(E13*C13) -> 20 | G13: 0.4 | H13: =SUM((F13*G13)+F13) -> 28
A14: Impressção Vinil + Laminação | B14: Leiripantone | C14: 15 | D14: 2 | E14: 3.35 | F14: =SUM(E14*C14) -> 50.25 | G14: 0.2 | H14: =SUM((F14*G14)+F14) -> 60.3 | I14: 20
A15: vinil impresso s/ corte - 15.00€m2 | B15: NHM | C15: 16 | D15: 1 | E15: 2.877 | F15: =SUM(E15*C15) -> 46.032 | G15: 0.4 | H15: =SUM((F15*G15)+F15) -> 64.4448
A16: vinil impresso c/ corte - 18.00€m2 | B16: NHM | C16: 19 | D16: 1 | E16: 1.1645 | F16: =SUM(E16*C16) -> 22.1255 | G16: 0.4 | H16: =SUM((F16*G16)+F16) -> 30.9757
A17: vinil impresso + laminação - 25.00€m2 | B17: NHM | C17: 26 | D17: 1 | E17: 3.288 | F17: =SUM(E17*C17) -> 85.488 | G17: 0.4 | H17: =SUM((F17*G17)+F17) -> 119.6832
A18: impressão UV plana s/branco - 10.00€m2 | B18: NHM | C18: 11 | D18: 1 | E18: 1 | F18: =SUM(E18*C18) -> 11 | G18: 0.4 | H18: =SUM((F18*G18)+F18) -> 15.4
A19: impressão UV plana c/branco - 12.00€m2 | B19: NHM | C19: 13 | D19: 1 | E19: 1 | F19: =SUM(E19*C19) -> 13 | G19: 0.4 | H19: =SUM((F19*G19)+F19) -> 18.2
D20: 0 | F20: =SUM(E20*C20) -> 0 | G20: 0.4 | H20: =SUM((F20*G20)+F20) -> 0
D21: 0 | F21: =SUM(E21*C21) -> 0 | G21: 0.4 | H21: =SUM((F21*G21)+F21) -> 0
D22: 0 | F22: =SUM(E22*C22) -> 0 | G22: 0.4 | H22: =SUM((F22*G22)+F22) -> 0
D23: 0 | F23: =SUM(E23*C23) -> 0 | G23: 0.4 | H23: =SUM((F23*G23)+F23) -> 0
D24: 0 | F24: =SUM(E24*C24) -> 0 | G24: 0.4 | H24: =SUM((F24*G24)+F24) -> 0

Sheet ENVELOPES
A1: IMPRESSÃO | D1: ENVELOPES
A2: FORMATO DE IMPRESSÃO | B2: CUSTO DE IMPRESSÃO | D2: FORMATO | E2: TIPO | G2: CUSTO UNITÁRIO
A3: IMPRESSÃO DL | B3: 0.12 | D3: DL 90 | E3: JANELA | F3: 0 | G3: 500 | H3: =F3/G3 -> 0
E4: S JANELA | F4: 44.5 | G4: 1000 | H4: =F4/G4 -> 0.0445
D5: DL 120 | E5: JANELA | F5: 0 | G5: 500 | H5: =F5/G5 -> 0
E6: S JANELA | F6: 61.97 | G6: 500 | H6: =F6/G6 -> 0.12394
A10: CÁLCULO DE IMPRESSÕES
A11: CLIENTE | B11: DESCRIÇÃO | C11: QUANT. | D11: CUSTO UNIT. IMP. | E11: CUSTO IMPRESSÃO | F11: CUSTO UNIT. PAPEL | G11: CUSTO PAPEL | H11: CUSTO TOTAL PROD. | I11: % LUCRO | J11: TOTAL | K11: TOTAL UNITÁRIO
A12: RIVER BUILD | B12: ENVELOPES DL | C12: 50 | D12: 0.12 | E12: =C12*D12 -> 6 | F12: 0.05 | G12: =C12*F12 -> 2.5 | H12: =G12+E12 -> 8.5 | I12: 3 | J12: =SUM(H12*I12)+H12 -> 34 | K12: =SUM(J12/C12) -> 0.68
A13: RIVER BUILD | B13: ENVELOPES DL | C13: 500 | D13: 0.12 | E13: =C13*D13 -> 60 | F13: 0.03 | G13: =C13*F13 -> 15 | H13: =G13+E13 -> 75 | I13: 3 | J13: =SUM(H13*I13)+H13 -> 300 | K13: =SUM(J13/C13) -> 0.6
A14: RIVER BUILD | B14: ENVELOPES DL | C14: 1000 | D14: 0.12 | E14: =C14*D14 -> 120 | F14: 0.03 | G14: =C14*F14 -> 30 | H14: =G14+E14 -> 150 | I14: 3 | J14: =SUM(H14*I14)+H14 -> 600 | K14: =SUM(J14/C14) -> 0.6
A15: DIGIWEST | B15: ENVELOPES DL | C15: 250 | D15: 0.12 | E15: =C15*D15 -> 30 | F15: 0.03 | G15: =C15*F15 -> 7.5 | H15: =G15+E15 -> 37.5 | I15: 3 | J15: =SUM(H15*I15)+H15 -> 150 | K15: =SUM(J15/C15) -> 0.6
A16: Joana | B16: ENVELOPES DL | C16: 200 | D16: 0.12 | E16: =C16*D16 -> 24 | F16: 0.03 | G16: =C16*F16 -> 6 | H16: =G16+E16 -> 30 | I16: 0.2 | J16: =SUM(H16*I16)+H16 -> 36 | K16: =SUM(J16/C16) -> 0.18
A17: Joana | B17: ENVELOPES DL | C17: 500 | D17: 0.12 | E17: =C17*D17 -> 60 | F17: 0.03 | G17: =C17*F17 -> 15 | H17: =G17+E17 -> 75 | I17: 0.2 | J17: =SUM(H17*I17)+H17 -> 90 | K17: =SUM(J17/C17) -> 0.18 | L17: =J17*1.23 -> 110.7
A18: Joana | B18: ENVELOPES DL | C18: 500 | D18: 0.12 | E18: =C18*D18 -> 60 | F18: 0.12 | G18: =C18*F18 -> 60 | H18: =G18+E18 -> 120 | I18: 0.2 | J18: =SUM(H18*I18)+H18 -> 144 | K18: =SUM(J18/C18) -> 0.288 | L18: =J18*1.23 -> 177.12
A19: PIANOS | B19: ENVELOPES DL | C19: 100 | D19: 0.12 | E19: =C19*D19 -> 12 | F19: 0.03 | G19: =C19*F19 -> 3 | H19: =G19+E19 -> 15 | I19: 3 | J19: =SUM(H19*I19)+H19 -> 60 | K19: =SUM(J19/C19) -> 0.6
B20: ENVELOPES DL | C20: 500 | D20: 0.12 | E20: =C20*D20 -> 60 | F20: 0.03 | G20: =C20*F20 -> 15 | H20: =G20+E20 -> 75 | I20: 3 | J20: =SUM(H20*I20)+H20 -> 300 | K20: =SUM(J20/C20) -> 0.6
A21: BFERREIRA | B21: ENVELOPES DL | C21: 100 | D21: 0.12 | E21: =C21*D21 -> 12 | F21: 0.04 | G21: =C21*F21 -> 4 | H21: =G21+E21 -> 16 | I21: 2 | J21: =SUM(H21*I21)+H21 -> 48 | K21: =SUM(J21/C21) -> 0.48

Sheet PASTAS PARA A4
A1: IMPRESSÃO | D1: PAPEL | H1: CORTE | K1: PLASTIFICAÇÃO | Q1: DOBRA
A2: FORMATO DE IMPRESSÃO | B2: CUSTO DE IMPRESSÃO | D2: FORMATO | E2: GRAMAGEM | F2: CUSTO UNITÁRIO | H2: CORTE | I2: CUSTO UNITÁRIO | L2: CUSTO UNITÁRIO | N2: QUANT. | O2: CUSTO TOTAL | Q2: DOBRA | R2: CUSTO UNITÁRIO
A3: SRA3 CMYK SÓ FRENTE | B3: 0.09 | D3: SRA3 | E3: 250 | F3: =SUM(PAPEL!G7) -> 0.09458 | H3: NORMAL | I3: =SUM(ACABAMENTO!B3) -> 0.02 | K3: < 100 | L3: =SUM(ACABAMENTO!C13) -> 0.5 | N3: 50 | O3: =SUM(L3*N3) -> 25 | Q3: NORMAL | R3: 0.07
E4: 300 | F4: =SUM(PAPEL!G8) -> 0.06 | K4: < 500 | L4: =SUM(ACABAMENTO!C14) -> 0.34 | N4: 300 | O4: =SUM(L4*N4) -> 102
E5: 400 | F5: =PAPEL!G10 -> 0.14328 | K5: > 500 | L5: =SUM(ACABAMENTO!C15) -> 0.17 | N5: 0 | O5: =SUM(L5*N5) -> 0
L6: A TRANSPORTAR | O6: =SUM(O3:O5) -> 127
A7: BOLSA | D7: FERRAGEM
A8: BOLSA | B8: CUSTO UNITÁRIO | D8: FERRAGEM | E8: CUSTO UNITÁRIO
A9: NORMAL | B9: 0.5 | D9: NORMAL | E9: 0.5
A12: CÁLCULO DE IMPRESSÕES | I12: CUSTOS DE ACABAMENTO
A13: CLIENTE | B13: DESCRIÇÃO | C13: QUANT. | D13: QUANT. PAPEL | E13: CUSTO UNIT. IMP. | F13: CUSTO IMPRESSÃO | G13: CUSTO UNIT. PAPEL | H13: CUSTO PAPEL | I13: CORTE | J13: PLAST. | K13: FOIL | L13: DOBRA | M13: FERRAGEM | N13: BOLSA | O13: CUSTO TOTAL PROD. | P13: CUSTO UNIT. PROD. | Q13: % LUCRO | R13: TOTAL | S13: TOTAL UNITÁRIO
A14: NX ARQUITETOS | B14: PASTAS A4 IMP. 1 LADO PLASTI 1 LADO BOLSA | C14: 50 | D14: =C14 -> 50 | E14: =B3 -> 0.09 | F14: =SUM(E14*D14) -> 4.5 | G14: 0.14 | H14: =SUM(D14*G14) -> 7 | I14: =SUM(I3*D14) -> 1 | J14: 25 | K14: 0 | L14: =C14*R3 -> 3.5 | N14: =B9*C14 -> 25 | O14: =F14+H14+I14+J14+K14+L14+N14 -> 66 | P14: =O14/C14 -> 1.32 | Q14: 3 | R14: =SUM((O14*Q14)+O14) -> 264 | S14: =SUM(R14/C14) -> 5.28
A15: NX ARQUITETOS | B15: PASTAS A4 IMP. 1 LADO PLASTI 1 LADO BOLSA | C15: 80 | D15: =C15 -> 80 | E15: =B3 -> 0.09 | F15: =SUM(E15*D15) -> 7.2 | G15: 0.14 | H15: =SUM(D15*G15) -> 11.2 | I15: =SUM(I3*D15) -> 1.6 | J15: 40 | K15: 0 | L15: =C15*R3 -> 5.6 | N15: =B9*C15 -> 40 | O15: =F15+H15+I15+J15+K15+L15+N15 -> 105.6 | P15: =O15/C15 -> 1.32 | Q15: 3 | R15: =SUM((O15*Q15)+O15) -> 422.4 | S15: =SUM(R15/C15) -> 5.28
A16: NX ARQUITETOS | B16: PASTAS A4 IMP. 1 LADO PLASTI 1 LADO BOLSA | C16: 100 | D16: =C16 -> 100 | E16: =B3 -> 0.09 | F16: =SUM(E16*D16) -> 9 | G16: 0.14 | H16: =SUM(D16*G16) -> 14 | I16: =SUM(I3*D16) -> 2 | J16: 50 | K16: 0 | L16: =C16*R3 -> 7 | N16: =B9*C16 -> 50 | O16: =F16+H16+I16+J16+K16+L16+N16 -> 132 | P16: =O16/C16 -> 1.32 | Q16: 3 | R16: =SUM((O16*Q16)+O16) -> 528 | S16: =SUM(R16/C16) -> 5.28
A17: NX ARQUITETOS | B17: PASTAS A4 IMP. 1 LADO PLASTI 1 LADO BOLSA | C17: 125 | D17: =C17 -> 125 | E17: =B3 -> 0.09 | F17: =SUM(E17*D17) -> 11.25 | G17: 0.14 | H17: =SUM(D17*G17) -> 17.5 | I17: =SUM(I3*D17) -> 2.5 | J17: 42.5 | K17: 0 | L17: =C17*R3 -> 8.75 | N17: =B9*C17 -> 62.5 | O17: =F17+H17+I17+J17+K17+L17+N17 -> 145 | P17: =O17/C17 -> 1.16 | Q17: 3 | R17: =SUM((O17*Q17)+O17) -> 580 | S17: =SUM(R17/C17) -> 4.64
A18: NX ARQUITETOS | B18: PASTAS A4 IMP. 1 LADO PLASTI 1 LADO BOLSA | C18: 150 | D18: =C18 -> 150 | E18: =B3 -> 0.09 | F18: =SUM(E18*D18) -> 13.5 | G18: 0.14 | H18: =SUM(D18*G18) -> 21 | I18: =SUM(I3*D18) -> 3 | J18: 51 | K18: 0 | L18: =C18*R3 -> 10.5 | N18: =B9*C18 -> 75 | O18: =F18+H18+I18+J18+K18+L18+N18 -> 174 | P18: =O18/C18 -> 1.16 | Q18: 3 | R18: =SUM((O18*Q18)+O18) -> 696 | S18: =SUM(R18/C18) -> 4.64
A19: NX ARQUITETOS | B19: PASTAS A4 IMP. 1 LADO PLASTI 1 LADO BOLSA | C19: 175 | D19: =C19 -> 175 | E19: =B3 -> 0.09 | F19: =SUM(E19*D19) -> 15.75 | G19: 0.14 | H19: =SUM(D19*G19) -> 24.5 | I19: =SUM(I3*D19) -> 3.5 | J19: 59.5 | K19: 0 | L19: =C19*R3 -> 12.25 | N19: =B9*C19 -> 87.5 | O19: =F19+H19+I19+J19+K19+L19+N19 -> 203 | P19: =O19/C19 -> 1.16 | Q19: 3 | R19: =SUM((O19*Q19)+O19) -> 812 | S19: =SUM(R19/C19) -> 4.64
A20: CHUCKING UP | B20: PASTAS A4 IMP. 1 LADO PLASTI 1 LADO BOLSA | C20: 150 | D20: =C20 -> 150 | E20: =B3 -> 0.09 | F20: =SUM(E20*D20) -> 13.5 | G20: 0.14 | H20: =SUM(D20*G20) -> 21 | I20: 3 | J20: 51 | K20: 0 | L20: 10.5 | N20: 75 | O20: =F20+H20+I20+J20+K20+L20+N20 -> 174 | P20: =O20/C20 -> 1.16 | Q20: 3 | R20: =SUM((O20*Q20)+O20) -> 696 | S20: =SUM(R20/C20) -> 4.64
A21: RIVERBUILD | B21: PASTAS A4 IMP. 1 LADO PLASTI 1 LADO BOLSA | C21: 50 | D21: =C21 -> 50 | E21: =B3 -> 0.09 | F21: =SUM(E21*D21) -> 4.5 | G21: 0.14 | H21: =SUM(D21*G21) -> 7 | I21: =SUM(I10*D21) -> 0 | J21: 25 | K21: 0 | L21: 3.5 | N21: =B9*C21 -> 25 | O21: =F21+H21+I21+J21+K21+L21+N21 -> 65 | P21: =O21/C21 -> 1.3 | Q21: 3 | R21: =SUM((O21*Q21)+O21) -> 260 | S21: =SUM(R21/C21) -> 5.2
A22: DESENHOS CRIATIVOS | B22: PASTAS A4 IMP. 1 LADO PLASTI 1 LADO + FOIL DOURADO BOLSA | C22: 200 | D22: =C22 -> 200 | E22: =B3 -> 0.09 | F22: =SUM(E22*D22) -> 18 | G22: 0.14 | H22: =SUM(D22*G22) -> 28 | I22: =SUM(I3*D22) -> 4 | J22: 68 | K22: 170 | L22: =R3*D22 -> 14 | N22: =B9*C22 -> 100 | O22: =F22+H22+I22+J22+K22+L22+N22 -> 402 | P22: =O22/C22 -> 2.01 | Q22: 3 | R22: =SUM((O22*Q22)+O22) -> 1608 | S22: =SUM(R22/C22) -> 8.04
A23: Silaco | B23: PASTAS A4 IMP. 1 LADO PLASTI 1 LADO + BOLSA | C23: 50 | D23: =C23 -> 50 | E23: =B3 -> 0.09 | F23: =SUM(E23*D23) -> 4.5 | G23: 0.14 | H23: =SUM(D23*G23) -> 7 | I23: 4 | J23: 8.5 | K23: 0 | L23: =R3*D23 -> 3.5 | N23: =B9*C23 -> 25 | O23: =F23+H23+I23+J23+K23+L23+N23 -> 52.5 | P23: =O23/C23 -> 1.05 | Q23: 3 | R23: =SUM((O23*Q23)+O23) -> 210 | S23: =SUM(R23/C23) -> 4.2
A24: Silaco | B24: PASTAS A4 IMP. 1 LADO PLASTI 1 LADO + BOLSA | C24: 50 | D24: =C24 -> 50 | E24: =B3 -> 0.09 | F24: =SUM(E24*D24) -> 4.5 | G24: 0.14 | H24: =SUM(D24*G24) -> 7 | I24: 4 | J24: 8.5 | K24: 0 | L24: =R3*D24 -> 3.5 | N24: 25 | O24: =F24+H24+I24+J24+K24+L24+N24 -> 52.5 | P24: =O24/C24 -> 1.05 | Q24: 3 | R24: =SUM((O24*Q24)+O24) -> 210 | S24: =SUM(R24/C24) -> 4.2
A25: Silaco | B25: PASTAS A4 IMP. 1 LADO PLASTI 1 LADO + BOLSA | C25: 100 | D25: =C25 -> 100 | E25: =B3 -> 0.09 | F25: =SUM(E25*D25) -> 9 | G25: 0.14 | H25: =SUM(D25*G25) -> 14 | I25: =SUM(I3*D25) -> 2 | J25: 34 | K25: 0 | L25: =R3*D25 -> 7 | N25: =B9*D25 -> 50 | O25: =F25+H25+I25+J25+K25+L25+N25+M25 -> 116 | P25: =O25/C25 -> 1.16 | Q25: 3 | R25: =SUM((O25*Q25)+O25) -> 464 | S25: =SUM(R25/C25) -> 4.64 | T25: 45540
A26: Silaco | B26: PASTAS A4 IMP. 1 LADO PLASTI 1 LADO + FERRAGEM | C26: 250 | D26: =C26 -> 250 | E26: =B3 -> 0.09 | F26: =SUM(E26*D26) -> 22.5 | G26: 0.14 | H26: =SUM(D26*G26) -> 35 | I26: =SUM(I3*D26) -> 5 | J26: 85 | K26: 0 | L26: =R3*D26 -> 17.5 | M26: =C26*E9 -> 125 | N26: 0 | O26: =F26+H26+I26+J26+K26+L26+N26+M26 -> 290 | P26: =O26/C26 -> 1.16 | Q26: 3 | R26: =SUM((O26*Q26)+O26) -> 1160 | S26: =SUM(R26/C26) -> 4.64 | T26: 45541
A27: Silaco | B27: PASTAS A4 IMP. 1 LADO PLASTI 1 LADO + FERRAGEM | C27: 300 | D27: =C27/2 -> 150 | E27: 0.09 | F27: =SUM(E27*D27) -> 13.5 | G27: 0.14 | H27: =SUM(D27*G27) -> 21 | I27: =SUM(I4*D27) -> 0 | J27: 102 | K27: 0 | L27: =R4*D27 -> 0 | M27: =C27*E10 -> 0 | N27: =C27*B9 -> 150 | O27: =F27+H27+I27+J27+K27+L27+N27+M27 -> 286.5 | P27: =O27/C27 -> 0.955 | Q27: 3 | R27: =SUM((O27*Q27)+O27) -> 1146 | S27: =SUM(R27/C27) -> 3.82 | T27: 45541
R28: =SUM((O28*Q28)+O28) -> 0
R29: =SUM((O29*Q29)+O29) -> 0

Sheet FLEX
A1: FLEX
A2: Medida | B2: Custo Unitário | D2: PERSONALIZAÇÃO DE POSTES | I2: PERSONALIZAÇÃO DE TENDAS
A3: 10 x 10 | B3: 1.15 | D3: Nr de logos por lado | F3: Preço | I3: FACES | J3: LOGOS tamanho | L3: PREÇO Material | M3: mao obra tempo | N3: 35 | O3: logos tamanho | P3: PREÇO Material | Q3: mao obra tempo | R3: 35
A4: 21 x 10 | B4: 1.75 | D4: Postes 1 Frente | F4: =E4*B4 -> 0 | I4: 1-face | J4: 120x17 | L4: 13.68 | M4: =0.5*N3 -> 17.5 | N4: =L4+M4 -> 31.18 | O4: 240x17 | P4: 26.27 | Q4: =0.5*R3 -> 17.5 | R4: =P4+Q4 -> 43.77
A5: 21 x 20 | B5: 2.5 | D5: Postes F/V até 10cm | E5: 3 | F5: =(E5*B3)*2 -> 6.9 | I5: 2-faces | J5: 120x17 | L5: 27.04 | M5: =0.5*N3 -> 17.5 | N5: =L5+M5 -> 44.54 | O5: 240x17 | P5: 52.54 | Q5: =0.5*R3 -> 17.5 | R5: =P5+Q5 -> 70.04
A6: 23x20 +- | B6: 2.7 | D6: Postes F/V até 21cm | E6: 3 | F6: =(E6*B4)*2 -> 10.5 | I6: 3-faces | J6: 120x17 | L6: 40.72 | M6: =1*N3 -> 35 | N6: =L6+M6 -> 75.72 | O6: 240x17 | P6: 78.81 | Q6: =1*R3 -> 35 | R6: =P6+Q6 -> 113.81
A7: 30 x 21 | B7: 3.2 | I7: 4-faces | J7: 120x17 | L7: 54.08 | M7: =1.5*N3 -> 52.5 | N7: =L7+M7 -> 106.58 | O7: 240x17 | P7: 105.07 | Q7: =1.5*R3 -> 52.5 | R7: =P7+Q7 -> 157.57
A10: CLIENTE | B10: PRODUTO | C10: MODELO | D10: CUSTO SUPORTE | E10: VALOR COM % | F10: IMPRESSÃO | G10: FRENTE | H10: VERSO | I10: CUSTO IMPRESSÃO | J10: CUSTO PRODUÇÃO UNITÁRIO | K10: % LUCRO | L10: TOTAL UNITÁRIO
A11: João Vitorino | B11: T-shirts | C11: TH ANKHARA | D11: 2.649 | E11: =SUM((D11*40%)+D11) -> 3.7086 | F11: DTF | G11: 1.15 | H11: 2.3 | I11: =SUM(G11+H11) -> 3.45 | J11: =D11+I11 -> 6.099 | K11: 0.4 | L11: =SUM((D11*K11)+D11+I11) -> 7.1586 | M11: =L11*50 -> 357.93
A12: João Vitorino | B12: T-shirts | C12: ROLY BEAGLE | D12: 2.13 | E12: =SUM((D12*40%)+D12) -> 2.982 | F12: DTF | G12: 1.15 | H12: 2.3 | I12: =SUM(G12+H12) -> 3.45 | J12: =D12+I12 -> 5.58 | K12: 0.4 | L12: =SUM((D12*K12)+D12+I12) -> 6.432 | M12: =L12*50 -> 321.6
A13: CNE POUSOS | B13: T-shirts | C13: ROLY STAFFORD OPÇÃO simples | D13: 2.65 | E13: =SUM((D13*40%)+D13) -> 3.71 | F13: HEV/DTF | G13: 1.15 | H13: 2.5 | I13: =SUM(G13+H13) -> 3.65 | J13: =D13+I13 -> 6.3 | K13: 0.4 | L13: =SUM((D13*K13)+D13+I13) -> 7.36
A14: CNE POUSOS | B14: T-shirts | C14: ROLY STAFFORD OPÇÃO F/V | D14: 2.72375 | E14: =SUM((D14*40%)+D14) -> 3.81325 | F14: HEV/DTF | G14: 2.5 | H14: 2.5 | I14: =SUM(G14+H14) -> 5 | J14: =D14+I14 -> 7.72375 | K14: 0.4 | L14: =SUM((D14*K14)+D14+I14) -> 8.81325
A15: CNE POUSOS | B15: T-shirts | C15: ROLY STAFFORD CRIANÇA OPÇAO 1 | D15: 2.074 | E15: =SUM((D15*40%)+D15) -> 2.9036 | F15: HEV/DTF | G15: 1.15 | H15: 0 | I15: =SUM(G15+H15) -> 1.15 | J15: =D15+I15 -> 3.224 | K15: 0.4 | L15: =SUM((D15*K15)+D15+I15) -> 4.0536
A16: CNE BATALHA | B16: T-shirts | C16: ROLY BEAGLE | D16: 2.2617391 | E16: =SUM((D16*40%)+D16) -> 3.1664348 | F16: DTF | H16: 2.5 | I16: =SUM(G16+H16) -> 2.5 | J16: =D16+I16 -> 4.7617391 | K16: 0.4 | L16: =SUM((D16*K16)+D16+I16) -> 5.6664348
A17: TERRAÇOS | B17: T-shirts | C17: COLETES | D17: 1.1 | E17: =SUM((D17*40%)+D17) -> 1.54 | F17: FLEX | G17: 1.15 | H17: 1.75 | I17: =SUM(G17+H17) -> 2.9 | J17: =D17+I17 -> 4 | K17: 0.4 | L17: =SUM((D17*K17)+D17+I17) -> 4.44 | M17: =G17+H17+D17 -> 4
A18: zircom | B18: polo | C18: carpe | D18: 7 | E18: =SUM((D18*40%)+D18) -> 9.8 | F18: FLEX | G18: 1.15 | H18: 1.2 | I18: =SUM(G18+H18) -> 2.35 | J18: =E18+I18 -> 12.15 | K18: 0.4 | L18: =SUM((D18*K18)+D18+I18) -> 12.15
A19: catarina | B19: sweat | C19: COLETES | D19: 10.13 | E19: =SUM((D19*40%)+D19) -> 14.182 | F19: FLEX | G19: 1.15 | H19: 2.7 | I19: =SUM(G19+H19) -> 3.85 | J19: =D19+I19 -> 13.98 | K19: 0.4 | L19: =SUM((D19*K19)+D19+I19) -> 18.032 | M19: =G19+H19+E19 -> 18.032 | N19: =M19*19+5.95 -> 348.558 | O19: =N19/19 -> 18.345158
A20: vera | B20: tshirt | C20: Roly atomic 100un | D20: 1.24 | E20: =SUM((D20*40%)+D20) -> 1.736 | F20: FLEX | G20: 2.5 | H20: 0 | I20: =SUM(G20+H20) -> 2.5 | J20: =D20+I20 -> 3.74 | K20: 0.4 | L20: =SUM((D20*K20)+D20+I20) -> 4.236 | M20: =G20+H20+E20 -> 4.236 | N20: =M20*19+5.95 -> 86.434 | O20: =N20/19 -> 4.5491579
A21: vera | B21: tshirt | C21: Roly atomic | D21: 1.39 | E21: =SUM((D21*40%)+D21) -> 1.946 | F21: FLEX | G21: 2.5 | H21: 0 | I21: =SUM(G21+H21) -> 2.5 | J21: =D21+I21 -> 3.89 | K21: 0.4 | L21: =SUM((D21*K21)+D21+I21) -> 4.446 | M21: =G21+H21+E21 -> 4.446 | N21: =M21*19+5.95 -> 90.424 | O21: =N21/19 -> 4.7591579
A22: Festas pederneira | B22: tshirt | C22: TH Luanda | D22: 1.8195 | E22: =SUM((D22*40%)+D22) -> 2.5473 | F22: DTF | G22: 3.2 | H22: 1.75 | I22: =SUM(G22+H22) -> 4.95 | J22: =D22+I22 -> 6.7695 | K22: 0.4 | L22: =SUM((D22*K22)+D22+I22) -> 7.4973 | M22: =G22+H22+E22 -> 7.4973 | N22: =M22*19+5.95 -> 148.3987 | O22: =N22/19 -> 7.8104579
I26: 1.208 | J26: 1.15

Sheet CARTOES PVC
A1: CARTÃO | E1: CARTUXO | J1: TEMPO PRODUÇÃO | N1: VALORES DE MERCADO
A2: TIPO | C2: CUSTO UNITÁRIO | E2: COR | F2: CUSTO CARTUXO | G2: CAPACIDADE ESTIMADA | H2: CUSTO UNITÁRIO | J2: FACES | K2: TEMPO MÉDIO (SEGUNDOS) | L2: TEMPO TOTAL PRODUÇÃO | N2: CONCORRENTE | O2: VALOR UNIT.
A3: BRANCO SIMPLES | C3: 0.09 | E3: CMYK | F3: 87 | G3: 300 | H3: =F3/G3 -> 0.29 | J3: QUANTIDADE | K3: 87 | N3: Pixarprinting | O3: 0.93
A4: BRANCO BANDA MAGNETICA | C4: 0 | E4: K | F4: 25 | G4: 2000 | H4: =F4/G4 -> 0.0125 | J4: FRENTE | K4: 45 | L4: =K3*K4 -> 3915 | O4: 0
A5: BRANCO CHIP | C5: 0 | E5: ATENÇÃO! IMPRESSÃO FRENTE E VERSO CONTABILIZA 2 IMPRESSÕES | J5: FRENTE E VERSO | K5: 90 | L5: =K5*K3 -> 7830 | O5: 0
A6: TRANSPARENTE | C6: 0 | O6: 0
J7: SEGUNDOS | K7: MINUTOS | L7: HORAS | O7: 0
J8: 2880 | K8: =J8/60 -> 48 | L8: =K8/60 -> 0.8 | O8: 0
A10: CUSTO PRODUÇÃO | H10: CÁLCULO VENDA
A11: CLIENTE | B11: DESCRIÇÃO | C11: QUANT. | D11: CUSTO UNIT. CARTÃO | E11: CUSTO UNIT. IMPRESSÃO | F11: CUSTO UNIT. PRODUÇÃO | G11: CUSTO TOTAL PRODUÇÃO | H11: LUCRO (%) | I11: PVP TOTAL | J11: PVP UNIT
A12: CAÇAURQ | B12: Impressão 4/0 | C12: 64 | D12: 0.09 | E12: 0.29 | F12: =D12+E12 -> 0.38 | G12: =F12*C12 -> 24.32 | H12: 3.5 | I12: =((H12*G12)+H12) -> 88.62 | J12: =I12/C12 -> 1.3846875
A13: NOF | B13: Impressão 4/0 | C13: 100 | D13: 0.09 | E13: 0.29 | F13: =D13+E13 -> 0.38 | G13: =F13*C13 -> 38 | H13: 3.5 | I13: =((H13*G13)+H13) -> 136.5 | J13: =I13/C13 -> 1.365
A14: Celia Bras | B14: Impressão 4/4 | C14: 25 | D14: 0.09 | E14: 0.58 | F14: =D14+E14 -> 0.67 | G14: =F14*C14 -> 16.75 | H14: 3.5 | I14: =((H14*G14)+H14) -> 62.125 | J14: =I14/C14 -> 2.485
A15: fet | B15: Impressão 4/4 | C15: 87 | D15: 0.09 | E15: 0.58 | F15: =D15+E15 -> 0.67 | G15: =F15*C15 -> 58.29 | H15: 1.466 | I15: =((H15*G15)+H15) -> 86.91914 | J15: =I15/C15 -> 0.99907057

Sheet ALVEOLAR
A1: CUSTO PRODUÇÃO DE PLACAS AVEOLAR
A2: Alveolar CARACTERÍSTICAS DO ALVEOLAR FORNECIDO | F2: DIMENSÃO | I2: IMPRESSÃO | M2: CUSTO
A4: TIPO | B4: LARGURA ( M ) | C4: COMPRIMENTO ( M ) | D4: CUSTO FORNECEDOR | E4: CUSTO M / 2 | F4: LARGURA ( M ) | G4: ALTURA ( M ) | H4: M / 2 | I4: LARGURA ( M ) | J4: ALTURA ( M ) | K4: CUSTO FORNECEDOR | L4: M / 2 | M4: CUSTO | N4: % LUCRO | O4: TOTAL UNITÁRIO
A5: Dipac Light White PP Multiwall Sheet \\2000x2000x 5mm 1,2m x 90 | B5: 2 | C5: 2 | D5: 16.34 | E5: =D5/(B5*C5) -> 4.085 | F5: 1.2 | G5: 0.9 | H5: =F5*G5 -> 1.08 | L5: =I5*J5*K5 -> 0 | M5: =E5*H5 -> 4.4118 | N5: 3 | O5: =SUM((M5*N5)+L5+M5) -> 17.6472
A6: Dipac Light White PP Multiwall Sheet \\2000x2000x 5mm 1m x 0,54 m | B6: 2 | C6: 2 | D6: 16.34 | E6: =D6/(B6*C6) -> 4.085 | F6: 1 | G6: 0.54 | H6: =F6*G6 -> 0.54 | I6: 1.05 | J6: 0.54 | K6: 9 | L6: =I6*J6*K6 -> 5.103 | M6: =E6*H6 -> 2.2059 | N6: 3 | O6: =SUM((M6*N6)+M6+L6) -> 13.9266
A7: Dipac Light White PP Multiwall Sheet \\2000x2000x 5mm 90 x 60 | B7: 2 | C7: 2 | D7: 16.34 | E7: =D7/(B7*C7) -> 4.085 | F7: 0.9 | G7: 0.6 | H7: =F7*G7 -> 0.54 | L7: =I7*J7*K7 -> 0 | M7: =E7*H7 -> 2.2059 | N7: 3 | O7: =SUM((M7*N7)+L7+M7) -> 8.8236
A8: Dipac Light White PP Multiwall Sheet \\2000x2000x 5mm 90 x 60 | B8: 2 | C8: 2 | D8: 16.34 | E8: =D8/(B8*C8) -> 4.085 | F8: 0.5 | G8: 0.38 | H8: =F8*G8 -> 0.19 | L8: =I8*J8*K8 -> 0 | M8: =E8*H8 -> 0.77615 | N8: 3 | O8: =SUM((M8*N8)+L8+M8) -> 3.1046
A9: Dipac Light White PP Multiwall Sheet \\2500x2000x 5mm 120 x 70 | B9: 2.5 | C9: 2 | D9: 20.42 | E9: =D9/(B9*C9) -> 4.084 | F9: 1.2 | G9: 0.7 | H9: =F9*G9 -> 0.84 | I9: 1.2 | J9: 0.7 | L9: =I9*J9*K9 -> 0 | M9: =E9*H9 -> 3.43056 | N9: 3 | O9: =SUM((M9*N9)+L9+M9) -> 13.72224
A10: Dipac High Perform White PP Multiwall Sh \\3040x2020x 3,5mm | B10: 3.04 | C10: 2.02 | D10: 16.33 | E10: =D10/(B10*C10) -> 2.6592626 | F10: 1.5 | G10: 1 | H10: =F10*G10 -> 1.5 | I10: 1.5 | J10: 1 | L10: =I10*J10*K10 -> 0 | M10: =E10*H10+K10 -> 3.988894 | N10: 3 | O10: =SUM((M10*N10)+L10+M10) -> 15.955576 | P10: =O10+33.6 -> 49.555576 | Q10: =M10+24 -> 27.988894
A11: Dipac High Perform White PP Multiwall Sh \\3040x2020x 3,5mm | B11: 3.04 | C11: 2.02 | D11: 16.33 | E11: =D11/(B11*C11) -> 2.6592626 | F11: 1.15 | G11: 0.65 | H11: =F11*G11 -> 0.7475 | I11: 1.15 | J11: 0.65 | L11: =I11*J11*K11 -> 0 | M11: =E11*H11+K11 -> 1.9877988 | N11: 3 | O11: =SUM((M11*N11)+L11+M11) -> 7.9511953 | P11: =O11+16.8 -> 24.751195 | Q11: =M11+12 -> 13.987799
A12: Dipac High Perform White PP Multiwall Sh \\3040x2020x 3,5mm | B12: 3.04 | C12: 2.02 | D12: 16.33 | E12: =D12/(B12*C12) -> 2.6592626 | F12: 0.6 | G12: 0.85 | H12: =F12*G12 -> 0.51 | I12: 0.6 | J12: 0.85 | L12: =I12*J12*K12 -> 0 | M12: =E12*H12+K12 -> 1.3562239 | N12: 3 | O12: =SUM((M12*N12)+L12+M12) -> 5.4248958 | P12: =O12+11.48 -> 16.904896 | Q12: =M12+8.2 -> 9.5562239
A13: PLACA FOAM LIGHT BRANCO 3050x2050x 5mm | B13: 3.05 | C13: 2.05 | D13: 65.22 | E13: =D13/(B13*C13) -> 10.431028 | F13: 1.5 | G13: 1 | H13: =F13*G13 -> 1.5 | I13: 1.5 | J13: 1 | L13: =I13*J13*K13 -> 0 | M13: =E13*H13+K13 -> 15.646541 | N13: 3 | O13: =SUM((M13*N13)+L13+M13) -> 62.586166 | P13: =O13+33.6 -> 96.186166 | Q13: =M13+24 -> 39.646541
A14: PLACA FOAM LIGHT BRANCO 3050x2050x 5mm | B14: 3.05 | C14: 2.05 | D14: 65.22 | E14: =D14/(B14*C14) -> 10.431028 | F14: 1.15 | G14: 0.65 | H14: =F14*G14 -> 0.7475 | I14: 1.15 | J14: 0.65 | L14: =I14*J14*K14 -> 0 | M14: =E14*H14+K14 -> 7.7971931 | N14: 3 | O14: =SUM((M14*N14)+L14+M14) -> 31.188772 | P14: =O14+16.8 -> 47.988772 | Q14: =M14+12 -> 19.797193
A15: PLACA FOAM LIGHT BRANCO 3050x2050x 5mm | B15: 3.05 | C15: 2.05 | D15: 65.22 | E15: =D15/(B15*C15) -> 10.431028 | F15: 0.6 | G15: 0.85 | H15: =F15*G15 -> 0.51 | I15: 0.6 | J15: 0.85 | L15: =I15*J15*K15 -> 0 | M15: =E15*H15+K15 -> 5.3198241 | N15: 3 | O15: =SUM((M15*N15)+L15+M15) -> 21.279296 | P15: =O15+11.48 -> 32.759296 | Q15: =M15+8.2 -> 13.519824
A16: PLACA FOAM LIGHT BRANCO 3050x2050x 4mm | B16: 3.05 | C16: 2.05 | D16: 55.83 | E16: =D16/(B16*C16) -> 8.9292283 | F16: 2.4 | G16: 1 | H16: =F16*G16 -> 2.4 | I16: 2.4 | J16: 1 | K16: 15 | L16: =I16*J16*K16 -> 36 | M16: =(E16*H16)+K16 -> 36.430148 | N16: 0.2 | O16: =SUM((M16*N16)+L16+M16) -> 79.716178 | P16: =O16+11.48 -> 91.196178 | Q16: =M16+8.2 -> 44.630148
A17: PLACA ACM 3 mm 1500x1000 | B17: 1.5 | C17: 1 | D17: 35.56 | E17: =D17/(B17*C17) -> 23.706667 | F17: 0.4 | G17: 0.6 | H17: =F17*G17 -> 0.24 | I17: 0.4 | J17: 0.6 | K17: 0 | L17: =(I17*J17)*K17 -> 0 | M17: =(E17*H17)+K17 -> 5.6896 | N17: 1 | O17: =SUM((M17*N17)+L17+M17) -> 11.3792 | P17: =O17+11.48 -> 22.8592 | Q17: =M17+8.2 -> 13.8896

Sheet VINIL
A1: CUSTO PRODUÇÃO DE VINIL
A2: VINIL CARACTERÍSTICAS DO VINIL FORNECIDO | F2: DIMENSÃO | I2: CUSTO
F3: LARGURA IGUAL AO ROLO
A4: TIPO | B4: LARGURA ( M ) | C4: COMPRIMENTO ( M ) | D4: CUSTO FORNECEDOR | E4: CUSTO M / 2 | F4: LARGURA ( M ) | G4: ALTURA ( M ) | H4: M / 2 | I4: CUSTO | J4: % LUCRO | K4: TOTAL UNITÁRIO
A5: Suptac S5001B Polar White Gloss 615mm x 5m | B5: 0.615 | C5: 5 | D5: 19.12 | E5: =D5/(B5*C5) -> 6.2178862 | F5: 0.615 | G5: 0.8 | H5: =F5*G5 -> 0.492 | I5: =E5*H5 -> 3.0592 | J5: 3 | K5: =SUM((I5*J5)+I5) -> 12.2368 | L5: =K5*2 -> 24.4736
A6: Suptac S5001B Polar White Gloss 615mm x 5m | B6: 0.615 | C6: 15 | D6: 64.59 | E6: =D6/(B6*C6) -> 7.001626 | F6: 0.615 | G6: 0.25 | H6: =F6*G6 -> 0.15375 | I6: =E6*H6 -> 1.0765 | J6: 3 | K6: =SUM((I6*J6)+I6) -> 4.306 | N6: 9.94 | O6: 3
A7: Suptac S5001B Suptac S5889B Coal Black Gloss 615mm x 5m | B7: 0.615 | C7: 5 | D7: 19.12 | E7: =D7/(B7*C7) -> 6.2178862 | F7: 0.615 | G7: 0.84 | H7: =F7*G7 -> 0.5166 | I7: =E7*H7 -> 3.21216 | J7: 1.5 | K7: =SUM((I7*J7)+I7) -> 8.0304 | N7: =N6*O6 -> 29.82
A8: Suptac S5001B Polar White Gloss 615mm x 5m | B8: 0.615 | C8: 5 | D8: 21.53 | E8: =D8/(B8*C8) -> 7.001626 | F8: 0.615 | G8: 0.121 | H8: =F8*G8 -> 0.074415 | I8: =E8*H8 -> 0.521026 | J8: 3 | K8: =SUM((I8*J8)+I8) -> 2.084104
A9: Suptac S5001B Polar White Gloss 615mm x 10m | B9: 0.615 | C9: 10 | D9: 43.06 | E9: =D9/(B9*C9) -> 7.001626 | F9: 0.615 | G9: 0.2 | H9: =F9*G9 -> 0.123 | I9: =E9*H9 -> 0.8612 | J9: 3 | K9: =SUM((I9*J9)+I9) -> 3.4448
A10: Ecotac E3877B Silver Gloss 615mm x 5m | B10: 0.615 | C10: 5 | D10: 15.9 | E10: =D10/(B10*C10) -> 5.1707317 | F10: 0.615 | G10: 0.5 | H10: =F10*G10 -> 0.3075 | I10: =E10*H10 -> 1.59 | J10: 3 | K10: =SUM((I10*J10)+I10) -> 6.36
A11: Ecotac E3151B Orange Gloss 615mm x 5m | B11: 0.615 | C11: 5 | D11: 12.85 | E11: =D11/(B11*C11) -> 4.1788618 | F11: 0.615 | G11: 2 | H11: =F11*G11 -> 1.23 | I11: =E11*H11 -> 5.14 | J11: 3 | K11: =SUM((I11*J11)+I11) -> 20.56
A12: FLEX BRANCO | B12: 0.5 | C12: 2.5 | D12: 20.12 | E12: =D12/(B12*C12) -> 16.096 | F12: 0.04 | G12: 0.81 | H12: 1.632 | I12: =E12*H12 -> 26.268672 | J12: 3 | K12: =SUM((I12*J12)+I12) -> 105.07469
A13: Suptac S5165B Mandarin Orange Gloss 615mm x 5m | B13: 0.615 | C13: 5 | D13: 26.03 | E13: =D13/(B13*C13) -> 8.4650407 | F13: 0.615 | G13: 4 | H13: =F13*G13 -> 2.46 | I13: =E13*H13 -> 20.824 | J13: 2 | K13: =SUM((I13*J13)+I13) -> 62.472
A14: FOSCO LT5510M Etched Glass Deep Silver Matt 1220mm x 5m | B14: 1.22 | C14: 5 | D14: 35.7 | E14: =D14/(B14*C14) -> 5.852459 | F14: 1.22 | G14: 4.2 | H14: =F14*G14 -> 5.124 | I14: =E14*H14 -> 29.988 | J14: 2 | K14: =SUM((I14*J14)+I14) -> 89.964
A15: Ecotac E3485M Fire Red Matt 615mm x 5m | B15: 0.615 | C15: 5 | D15: 13.5 | E15: =D15/(B15*C15) -> 4.3902439 | F15: 0.615 | G15: 0.25 | H15: =F15*G15 -> 0.15375 | I15: =E15*H15 -> 0.675 | J15: 2 | K15: =SUM((I15*J15)+I15) -> 2.025 | N15: =3*35+K19 -> 159.65475
A16: Ecotac azul Matt 615mm x 5m | B16: 0.615 | C16: 5 | D16: 13.5 | E16: =D16/(B16*C16) -> 4.3902439 | F16: 0.615 | G16: 2.8 | H16: =F16*G16 -> 1.722 | I16: =E16*H16 -> 7.56 | J16: 3 | K16: =SUM((I16*J16)+I16) -> 30.24 | L16: =K16+K17 -> 35.64
A17: Ecotac preto Matt 615mm x 5m | B17: 0.615 | C17: 5 | D17: 13.5 | E17: =D17/(B17*C17) -> 4.3902439 | F17: 0.615 | G17: 0.5 | H17: =F17*G17 -> 0.3075 | I17: =E17*H17 -> 1.35 | J17: 3 | K17: =SUM((I17*J17)+I17) -> 5.4 | L17: =I16+I17 -> 8.91 | N17: =N15/20 -> 7.9827375
A18: Luxtac S5ICEM Etched Glass ICE White Matt 1230mm x 5m 75,58€ | B18: 1.23 | C18: 5 | D18: 75.58 | E18: =D18/(B18*C18) -> 12.289431 | F18: 1.23 | G18: 2.65 | H18: =F18*G18 -> 3.2595 | I18: =E18*H18 -> 40.0574 | J18: 3 | K18: =SUM((I18*J18)+I18) -> 160.2296 | L18: =I17+I18 -> 41.4074
A19: Ecotac E3485B Fire Red Gloss 615mm x 10m | B19: 0.615 | C19: 10 | D19: 26.99 | E19: =D19/(B19*C19) -> 4.3886179 | F19: 0.615 | G19: 6.75 | H19: =F19*G19 -> 4.15125 | I19: =E19*H19 -> 18.21825 | J19: 2 | K19: =SUM((I19*J19)+I19) -> 54.65475

Sheet IMPRESSÃO UV
A1: Preço | E1: Calculo m2 placas | F1: Medida m2 | H1: Un. por gabarito | I1: preço | L1: CALCULO suporte imp. | M1: preço | N1: Nr. Placas | O1: tamanho corte | P1: qt. por placa | Q1: preço corte | R1: total
A2: Material | C2: Custo Unitário | E2: tamanho total | F2: 0.9 | G2: 0.6 | I2: =(F2*G2)*C4 -> 13.5 | L2: PVC 3050x1220x3mm | M2: 38.32 | N2: 3 | O2: 580x634 | P2: 45 | Q2: 12.6 | R2: =(M2*N2+Q2)/P2 -> 2.8346667
A3: DTF Uv (Folha A3) | C3: 8 | E3: Placa 20x20 AL | F3: 0.2 | G3: 0.2 | I3: =(F3*G3)*C4 -> 1
A4: Impressão UV (m2) | C4: 25 | E4: Canetas
E5: Lapis
A7: Calculo Preço C/ gabarito personalizado | B7: tamanho | C7: Largura | D7: Unidades plano | E7: Preço uni
B8: 0.45 | C8: 0.45 | D8: 24 | E8: =((B8*C8)/D8)*C4 -> 0.2109375
B11: Tamanho max imp. | D11: m2 | E11: Preço imp. | F11: por gabarito | G11: nr peças por suporte | H11: Preço un suporte de imp. | I11: Preço un imp+material | J11: TOTAL UNI. | K11: %Margem | L11: Total uni. c/ margem
B12: 60 | C12: 90 | D12: 0.54 | P12: 0.012 | Q12: 0.014
A13: Placa c/ 8un | B13: 58 | C13: 63.4 | D13: =B13*C13/10000 -> 0.36772 | E13: =D13*C4 -> 9.193 | F13: =E13*D4 -> 0 | G13: 10 | H13: =R2/G13 -> 0.28346667 | I13: =(G13/E13)+H13 -> 1.3712509 | L13: =(J13*K13)+J13 -> 0 | N13: Preço % | O13: 2.15 | P13: =O13*1.2 -> 2.58 | Q13: =O13*1.4 -> 3.01
B14: 50 | C14: 70 | D14: =B14*C14/10000 -> 0.35 | E14: =D14*C4 -> 8.75 | F14: =E14*D4 -> 0 | G14: 1 | H14: =R2/G14 -> 2.8346667 | I14: =(G14/E14)+H14 -> 2.9489524 | L14: =(J14*K14)+J14 -> 0 | O14: 2 | P14: =O14*1.2 -> 2.4 | Q14: =O14*1.4 -> 2.8
A15: Acrilico | B15: 9.5 | C15: 1.7 | D15: =B15*C15/10000 -> 0.001615 | E15: =D15*C4 -> 0.040375 | F15: =E15*D4 -> 0 | G15: 0 | H15: =P3/G15 -> #DIV/0! | I15: =(G15/E15)+H15 -> #DIV/0! | L15: =(J15*K15)+J15 -> 0 | O15: 2.3 | P15: =O15*1.2 -> 2.76 | Q15: =O15*1.4 -> 3.22
A16: Acrilico bola | B16: 8 | C16: 8 | D16: =B16*C16/10000 -> 0.0064 | E16: =D16*C4 -> 0.16 | F16: =E16*D4 -> 0 | G16: 1 | H16: =L4/G16 -> 0 | I16: =(G16/E16)+H16 -> 6.25 | L16: =(J16*K16)+J16 -> 0 | O16: 2.8 | P16: =O16*1.2 -> 3.36 | Q16: =O16*1.4 -> 3.92
A17: Acrilico bola | B17: 5.5 | C17: 5.5 | D17: =B17*C17/10000 -> 0.003025 | E17: =D17*C4 -> 0.075625 | F17: =E17*D4 -> 0 | G17: 1 | H17: 17.5 | I17: =(G17/E17)+H17 -> 30.72314 | L17: =(J17*K17)+J17 -> 0
A18: Placa 17x7 5mm | B18: 17 | C18: 0.7 | D18: =B18*C18/10000 -> 0.00119 | E18: =D18*C4 -> 0.02975 | F18: 0.38 | G18: 52 | H18: 2.15 | I18: =(H18+F18)*G18 -> 131.56 | J18: =I18/G18 -> 2.53 | K18: 0.2 | L18: =(J18*K18)+J18 -> 3.036
A19: Placa 20x20 | B19: 17 | C19: 0.7 | D19: =B19*C19/10000 -> 0.00119 | E19: =D19*C5 -> 0 | F19: 1.25 | G19: 2 | H19: 2 | I19: =(H19+F19)*G19 -> 6.5 | J19: =I19/G19 -> 3.25 | K19: 0.2 | L19: =(J19*K19)+J19 -> 3.9
A20: Placa 30x15 | B20: 5.5 | C20: 5.5 | D20: =B20*C20/10000 -> 0.003025 | E20: =D20*C4 -> 0.075625 | F20: 1.38 | G20: 8 | H20: 2.3 | I20: =(H20+F20)*G20 -> 29.44 | J20: =I20/G20 -> 3.68 | K20: 0.2 | L20: =(J20*K20)+J20 -> 4.416
A21: placa 40x70 | B21: 5.5 | C21: 5.5 | D21: =B21*C21/10000 -> 0.003025 | E21: =D21*C4 -> 0.075625 | F21: 7 | G21: 1 | H21: 2.8 | I21: =(H21+F21)*G21 -> 9.8 | J21: =I21/G21 -> 9.8 | K21: 0.2 | L21: =(J21*K21)+J21 -> 11.76
A22: Placa 17x7 5mm | B22: 17 | C22: 0.7 | D22: =B22*C22/10000 -> 0.00119 | E22: =D22*C4 -> 0.02975 | F22: 0.38 | G22: 52 | H22: 2.15 | I22: =(H22+F22)*G22 -> 131.56 | J22: =I22/G22 -> 2.53 | K22: 0.2 | L22: =(J22*K22)+J22 -> 3.036
A23: Placa 20x20 | B23: 17 | C23: 0.7 | D23: =B23*C23/10000 -> 0.00119 | E23: =D23*C4 -> 0.02975 | F23: 1.25 | G23: 2 | H23: 2 | I23: =(H23+F23)*G23 -> 6.5 | J23: =I23/G23 -> 3.25 | K23: 0.2 | L23: =(J23*K23)+J23 -> 3.9
A24: Placa 30x15 | B24: 5.5 | C24: 5.5 | D24: =B24*C24/10000 -> 0.003025 | E24: =D24*C4 -> 0.075625 | F24: 1.38 | G24: 8 | H24: 2.3 | I24: =(H24+F24)*G24 -> 29.44 | J24: =I24/G24 -> 3.68 | K24: 0.2 | L24: =(J24*K24)+J24 -> 4.416
A25: placa 40x70 | B25: 5.5 | C25: 5.5 | D25: =B25*C25/10000 -> 0.003025 | E25: =D25*C4 -> 0.075625 | F25: 7 | G25: 1 | H25: 2.8 | I25: =(H25+F25)*G25 -> 9.8 | J25: =I25/G25 -> 9.8 | K25: 0.2 | L25: =(J25*K25)+J25 -> 11.76
A26: Caderno Cirux | B26: 4.5 | C26: 4.5 | D26: =B26*C26/10000 -> 0.002025 | E26: =D26*C4 -> 0.050625 | F26: 0.21 | G26: 500 | H26: 0.78 | I26: =(H26+F26)*G26 -> 495 | J26: =I26/G26 -> 0.99 | K26: 0.4 | L26: =(J26*K26)+J26 -> 1.386
A27: Caderno Cirux | B27: 58 | C27: 63.4 | D27: =B27*C27/10000 -> 0.36772 | E27: =D27*C4 -> 9.193 | F27: 0 | G27: 1 | H27: 0.28 | I27: =(E27+H27+F27)*G27 -> 9.473 | J27: =I27/G27 -> 9.473 | K27: 0.2 | L27: =(J27*K27)+J27 -> 11.3676
A28: PLACA ACP IMPRESSA | B28: 95 | C28: 30 | D28: =B28*C28/10000 -> 0.285 | E28: =D28*C4 -> 7.125 | F28: 0 | G28: 1 | H28: 6 | I28: =(E28+H28+F28)*G28 -> 13.125 | J28: =I28/G28 -> 13.125 | K28: 0.2 | L28: =(J28*K28)+J28 -> 15.75
A29: caixa lapis | B29: 4 | C29: 4 | D29: =B29*C29/10000 -> 0.0016 | E29: =D29*C4 -> 0.04 | F29: 0 | G29: 100 | H29: 0.1 | I29: =(E29+H29+F29)*G29 -> 14 | J29: =I29/G29 -> 0.14 | K29: 0.4 | L29: =(J29*K29)+J29 -> 0.196
A30: caixa lapis | B30: 46 | C30: 32 | D30: =B30*C30/10000 -> 0.1472 | E30: =D30*C4 -> 3.68 | F30: 0 | G30: 21 | H30: 0.038 | I30: =(E30+H30+F30)*G30 -> 78.078 | J30: =I30/G30 -> 3.718 | K30: 0.4 | L30: =(J30*K30)+J30 -> 5.2052
A31: Placa PVC 5mm | B31: 50 | C31: 50 | D31: =B31*C31/10000 -> 0.25 | E31: =D31*C4 -> 6.25 | F31: 0 | G31: 2 | H31: 2.83 | I31: =(E31+H31)*G31 -> 18.16 | J31: =I31/G31 -> 9.08 | K31: 0.4 | L31: =(J31*K31)+J31 -> 12.712
A32: VINIL JOAO | B32: 55 | C32: 80 | D32: =B32*C32/10000 -> 0.44 | E32: =D32*C4 -> 11 | F32: 0 | G32: 64 | H32: 3.06 | I32: =(E32+H32) -> 14.06 | J32: =I32/G32 -> 0.2196875 | K32: 0.4 | L32: =(J32*K32)+J32 -> 0.3075625
A33: placa 20x60 João | B33: 20 | C33: 60 | D33: =B33*C33/10000 -> 0.12 | E33: =D33*C4 -> 3 | F33: 0 | G33: 1 | H33: 2.83 | I33: =(E33+H33+F33)*G33 -> 5.83 | J33: =I33/G33 -> 5.83 | K33: 0.4 | L33: =(J33*K33)+J33 -> 8.162

Sheet PRODUTOS PUBLICITÁRIOS
A1: CLIENTE | B1: PRODUTO | C1: Ref | D1: SUPORTE | E1: CUSTO SUPORTE | F1: IMPRESSÃO | G1: CUSTO IMPRESSÃO | H1: CUSTO PRODUÇÃO UNITÁRIO | I1: % LUCRO | J1: TOTAL UNITÁRIO
A2: TECOFIX | B2: ROLL UP | D2: Base Roll Up Weddt - 15,54 € | E2: 15.54 | F2: Tela 85x200 Leiripantone - 35 € | G2: 35 | H2: =E2+G2 -> 50.54 | I2: 0.4 | J2: =SUM((H2*I2)+H2) -> 70.756
A3: TECOFIX | B3: Bandeira Gota | D3: Estrutua Weddt Bandeira Gota 2,2m Suporte - 15,61 € Boia - 5,08 € Pé - 24,06 | E3: 44.75 | F3: Impressão e Acabamento Publifast - 32,39 € | G3: 32.39 | H3: =E3+G3 -> 77.14 | I3: 0.4 | J3: =SUM((H3*I3)+H3) -> 107.996
A4: RODRIGUES & GONÇALVES | B4: BALCÃO PANEL TRACK | D4: Balcaão WEDDT 100,42 € | E4: 100.42 | F4: Impressão NHM - 45 € | G4: 45 | H4: =E4+G4 -> 145.42 | I4: 0.4 | J4: =SUM((H4*I4)+H4) -> 203.588 | K4: Aplicação (RED) 45€
A5: WMG | B5: Balcao Promocional A | F5: Impressão NHM Peça 1 - 12 € Peça 2 - 60 | G5: 72 | H5: =E5+G5 -> 72 | I5: 0.2 | J5: =SUM((H5*I5)+H5) -> 86.4 | K5: 25
A6: ISCF | B6: ROLL UP | D6: Dimatur - 16,91 € | E6: 16.91 | F6: Tela rollup 85x200 Leiripantone - 55 € | G6: 35 | H6: =E6+G6 -> 51.91 | I6: 0.4 | J6: =SUM((H6*I6)+H6) -> 72.674
A7: ISCF | B7: ROLL UP | D7: Dimatur - 16,91 € | E7: 16.91 | F7: Tela / lona 85x200 NHM -30 € | G7: 30 | H7: =E7+G7 -> 46.91 | I7: 0.4 | J7: =SUM((H7*I7)+H7) -> 65.674
A8: Abbott | B8: ROLL UP | D8: Dimatur - 16,91 € | E8: 16.91 | F8: Tela / lona 85x200 NHM -30 € | G8: 30 | H8: =E8+G8 -> 46.91 | I8: 0.4 | J8: =SUM((H8*I8)+H8) -> 65.674
